{"version": "https://jsonfeed.org/version/1.1", "title": "照片集 Feed", "home_page_url": "https://xiaolin2004.github.io/gallery/grid-all", "feed_url": "https://xiaolin2004.github.io/gallery/feed.json", "description": "拿起相机，认真思考", "icon": "", "favicon": "", "authors": [{"name": "DonkeyKane"}], "language": "zh-CN", "follow_challenge": {"feedId": "55889147392629760", "userId": "41784388753060864"}, "items": [{"id": "https://raw.githubusercontent.com/xiaolin2004/gallery/master/Ryoanji/双松.webp", "url": "https://xiaolin2004.github.io/gallery?name=Ryoanji/双松.webp", "external_url": "https://xiaolin2004.github.io/gallery?name=Ryoanji/双松.webp", "title": "双松", "content_html": "<div><img src=\"https://raw.githubusercontent.com/xiaolin2004/gallery/master/Ryoanji/双松.webp\"/><p> - · - </p></div>", "image": "https://raw.githubusercontent.com/xiaolin2004/gallery/master/Ryoanji/双松.webp", "date_published": "2025-01-01 12:09:46", "date_modified": "2025-01-01 12:09:46"}, {"id": "https://raw.githubusercontent.com/xiaolin2004/gallery/master/Ryoanji/松.webp", "url": "https://xiaolin2004.github.io/gallery?name=Ryoanji/松.webp", "external_url": "https://xiaolin2004.github.io/gallery?name=Ryoanji/松.webp", "title": "松", "content_html": "<div><img src=\"https://raw.githubusercontent.com/xiaolin2004/gallery/master/Ryoanji/松.webp\"/><p> - · - </p></div>", "image": "https://raw.githubusercontent.com/xiaolin2004/gallery/master/Ryoanji/松.webp", "date_published": "2025-01-01 12:05:42", "date_modified": "2025-01-01 12:05:42"}, {"id": "https://raw.githubusercontent.com/xiaolin2004/gallery/master/Ryoanji/镜容池.webp", "url": "https://xiaolin2004.github.io/gallery?name=Ryoanji/镜容池.webp", "external_url": "https://xiaolin2004.github.io/gallery?name=Ryoanji/镜容池.webp", "title": "镜容池", "content_html": "<div><img src=\"https://raw.githubusercontent.com/xiaolin2004/gallery/master/Ryoanji/镜容池.webp\"/><p> - · - </p></div>", "image": "https://raw.githubusercontent.com/xiaolin2004/gallery/master/Ryoanji/镜容池.webp", "date_published": "2025-01-01 12:03:21", "date_modified": "2025-01-01 12:03:21"}, {"id": "https://raw.githubusercontent.com/xiaolin2004/gallery/master/Ryoanji/大东亚阵亡者冢.webp", "url": "https://xiaolin2004.github.io/gallery?name=Ryoanji/大东亚阵亡者冢.webp", "external_url": "https://xiaolin2004.github.io/gallery?name=Ryoanji/大东亚阵亡者冢.webp", "title": "大东亚阵亡者冢", "content_html": "<div><img src=\"https://raw.githubusercontent.com/xiaolin2004/gallery/master/Ryoanji/大东亚阵亡者冢.webp\"/><p> - · - </p></div>", "image": "https://raw.githubusercontent.com/xiaolin2004/gallery/master/Ryoanji/大东亚阵亡者冢.webp", "date_published": "2025-01-01 11:55:14", "date_modified": "2025-01-01 11:55:14"}, {"id": "https://raw.githubusercontent.com/xiaolin2004/gallery/master/Ryoanji/大东亚战争战死者告慰碑.webp", "url": "https://xiaolin2004.github.io/gallery?name=Ryoanji/大东亚战争战死者告慰碑.webp", "external_url": "https://xiaolin2004.github.io/gallery?name=Ryoanji/大东亚战争战死者告慰碑.webp", "title": "大东亚战争战死者告慰碑", "content_html": "<div><img src=\"https://raw.githubusercontent.com/xiaolin2004/gallery/master/Ryoanji/大东亚战争战死者告慰碑.webp\"/><p> - · - </p></div>", "image": "https://raw.githubusercontent.com/xiaolin2004/gallery/master/Ryoanji/大东亚战争战死者告慰碑.webp", "date_published": "2025-01-01 11:54:56", "date_modified": "2025-01-01 11:54:56"}, {"id": "https://raw.githubusercontent.com/xiaolin2004/gallery/master/Ryoanji/方丈庭院门.webp", "url": "https://xiaolin2004.github.io/gallery?name=Ryoanji/方丈庭院门.webp", "external_url": "https://xiaolin2004.github.io/gallery?name=Ryoanji/方丈庭院门.webp", "title": "方丈庭院门", "content_html": "<div><img src=\"https://raw.githubusercontent.com/xiaolin2004/gallery/master/Ryoanji/方丈庭院门.webp\"/><p> - · - </p></div>", "image": "https://raw.githubusercontent.com/xiaolin2004/gallery/master/Ryoanji/方丈庭院门.webp", "date_published": "2025-01-01 11:48:48", "date_modified": "2025-01-01 11:48:48"}, {"id": "https://raw.githubusercontent.com/xiaolin2004/gallery/master/Ryoanji/方丈庭园.webp", "url": "https://xiaolin2004.github.io/gallery?name=Ryoanji/方丈庭园.webp", "external_url": "https://xiaolin2004.github.io/gallery?name=Ryoanji/方丈庭园.webp", "title": "方丈庭园", "content_html": "<div><img src=\"https://raw.githubusercontent.com/xiaolin2004/gallery/master/Ryoanji/方丈庭园.webp\"/><p> - · - </p></div>", "image": "https://raw.githubusercontent.com/xiaolin2004/gallery/master/Ryoanji/方丈庭园.webp", "date_published": "2025-01-01 11:10:08", "date_modified": "2025-01-01 11:10:08"}, {"id": "https://raw.githubusercontent.com/xiaolin2004/gallery/master/Ryoanji/坐像.webp", "url": "https://xiaolin2004.github.io/gallery?name=Ryoanji/坐像.webp", "external_url": "https://xiaolin2004.github.io/gallery?name=Ryoanji/坐像.webp", "title": "坐像", "content_html": "<div><img src=\"https://raw.githubusercontent.com/xiaolin2004/gallery/master/Ryoanji/坐像.webp\"/><p> - · - </p></div>", "image": "https://raw.githubusercontent.com/xiaolin2004/gallery/master/Ryoanji/坐像.webp", "date_published": "2025-01-01 10:59:08", "date_modified": "2025-01-01 10:59:08"}, {"id": "https://raw.githubusercontent.com/xiaolin2004/gallery/master/Rokuonji/鸽子.webp", "url": "https://xiaolin2004.github.io/gallery?name=Rokuonji/鸽子.webp", "external_url": "https://xiaolin2004.github.io/gallery?name=Rokuonji/鸽子.webp", "title": "鸽子", "content_html": "<div><img src=\"https://raw.githubusercontent.com/xiaolin2004/gallery/master/Rokuonji/鸽子.webp\"/><p> - · - </p></div>", "image": "https://raw.githubusercontent.com/xiaolin2004/gallery/master/Rokuonji/鸽子.webp", "date_published": "2025-01-01 10:20:28", "date_modified": "2025-01-01 10:20:28"}, {"id": "https://raw.githubusercontent.com/xiaolin2004/gallery/master/Rokuonji/金阁寺chikawa.webp", "url": "https://xiaolin2004.github.io/gallery?name=Rokuonji/金阁寺chikawa.webp", "external_url": "https://xiaolin2004.github.io/gallery?name=Rokuonji/金阁寺chikawa.webp", "title": "金阁寺chikawa", "content_html": "<div><img src=\"https://raw.githubusercontent.com/xiaolin2004/gallery/master/Rokuonji/金阁寺chikawa.webp\"/><p> - · - </p></div>", "image": "https://raw.githubusercontent.com/xiaolin2004/gallery/master/Rokuonji/金阁寺chikawa.webp", "date_published": "2025-01-01 10:04:18", "date_modified": "2025-01-01 10:04:18"}, {"id": "https://raw.githubusercontent.com/xiaolin2004/gallery/master/Rokuonji/金阁寺.webp", "url": "https://xiaolin2004.github.io/gallery?name=Rokuonji/金阁寺.webp", "external_url": "https://xiaolin2004.github.io/gallery?name=Rokuonji/金阁寺.webp", "title": "金阁寺", "content_html": "<div><img src=\"https://raw.githubusercontent.com/xiaolin2004/gallery/master/Rokuonji/金阁寺.webp\"/><p> - · - </p></div>", "image": "https://raw.githubusercontent.com/xiaolin2004/gallery/master/Rokuonji/金阁寺.webp", "date_published": "2025-01-01 09:57:41", "date_modified": "2025-01-01 09:57:41"}, {"id": "https://raw.githubusercontent.com/xiaolin2004/gallery/master/Rokuonji/DSC_1646.32h9umlyiee0.webp", "url": "https://xiaolin2004.github.io/gallery?name=Rokuonji/DSC_1646.32h9umlyiee0.webp", "external_url": "https://xiaolin2004.github.io/gallery?name=Rokuonji/DSC_1646.32h9umlyiee0.webp", "title": "DSC_1646.32h9umlyiee0", "content_html": "<div><img src=\"https://raw.githubusercontent.com/xiaolin2004/gallery/master/Rokuonji/DSC_1646.32h9umlyiee0.webp\"/><p> - · - </p></div>", "image": "https://raw.githubusercontent.com/xiaolin2004/gallery/master/Rokuonji/DSC_1646.32h9umlyiee0.webp", "date_published": "2025-01-01 09:56:19", "date_modified": "2025-01-01 09:56:19"}, {"id": "https://raw.githubusercontent.com/xiaolin2004/gallery/master/Rokuonji/安民泽.webp", "url": "https://xiaolin2004.github.io/gallery?name=Rokuonji/安民泽.webp", "external_url": "https://xiaolin2004.github.io/gallery?name=Rokuonji/安民泽.webp", "title": "安民泽", "content_html": "<div><img src=\"https://raw.githubusercontent.com/xiaolin2004/gallery/master/Rokuonji/安民泽.webp\"/><p> - · - </p></div>", "image": "https://raw.githubusercontent.com/xiaolin2004/gallery/master/Rokuonji/安民泽.webp", "date_published": "2025-01-01 09:54:59", "date_modified": "2025-01-01 09:54:59"}, {"id": "https://raw.githubusercontent.com/xiaolin2004/gallery/master/Rokuonji/苔藓.webp", "url": "https://xiaolin2004.github.io/gallery?name=Rokuonji/苔藓.webp", "external_url": "https://xiaolin2004.github.io/gallery?name=Rokuonji/苔藓.webp", "title": "苔藓", "content_html": "<div><img src=\"https://raw.githubusercontent.com/xiaolin2004/gallery/master/Rokuonji/苔藓.webp\"/><p> - · - </p></div>", "image": "https://raw.githubusercontent.com/xiaolin2004/gallery/master/Rokuonji/苔藓.webp", "date_published": "2025-01-01 09:54:16", "date_modified": "2025-01-01 09:54:16"}, {"id": "https://raw.githubusercontent.com/xiaolin2004/gallery/master/Rokuonji/舍利殿-角.webp", "url": "https://xiaolin2004.github.io/gallery?name=Rokuonji/舍利殿-角.webp", "external_url": "https://xiaolin2004.github.io/gallery?name=Rokuonji/舍利殿-角.webp", "title": "舍利殿-角", "content_html": "<div><img src=\"https://raw.githubusercontent.com/xiaolin2004/gallery/master/Rokuonji/舍利殿-角.webp\"/><p> - · - </p></div>", "image": "https://raw.githubusercontent.com/xiaolin2004/gallery/master/Rokuonji/舍利殿-角.webp", "date_published": "2025-01-01 09:36:53", "date_modified": "2025-01-01 09:36:53"}, {"id": "https://raw.githubusercontent.com/xiaolin2004/gallery/master/Rokuonji/舍利殿金鹤.webp", "url": "https://xiaolin2004.github.io/gallery?name=Rokuonji/舍利殿金鹤.webp", "external_url": "https://xiaolin2004.github.io/gallery?name=Rokuonji/舍利殿金鹤.webp", "title": "舍利殿金鹤", "content_html": "<div><img src=\"https://raw.githubusercontent.com/xiaolin2004/gallery/master/Rokuonji/舍利殿金鹤.webp\"/><p> - · - </p></div>", "image": "https://raw.githubusercontent.com/xiaolin2004/gallery/master/Rokuonji/舍利殿金鹤.webp", "date_published": "2025-01-01 09:35:49", "date_modified": "2025-01-01 09:35:49"}, {"id": "https://raw.githubusercontent.com/xiaolin2004/gallery/master/Rokuonji/镜湖池.webp", "url": "https://xiaolin2004.github.io/gallery?name=Rokuonji/镜湖池.webp", "external_url": "https://xiaolin2004.github.io/gallery?name=Rokuonji/镜湖池.webp", "title": "镜湖池", "content_html": "<div><img src=\"https://raw.githubusercontent.com/xiaolin2004/gallery/master/Rokuonji/镜湖池.webp\"/><p> - · - </p></div>", "image": "https://raw.githubusercontent.com/xiaolin2004/gallery/master/Rokuonji/镜湖池.webp", "date_published": "2025-01-01 09:34:21", "date_modified": "2025-01-01 09:34:21"}, {"id": "https://raw.githubusercontent.com/xiaolin2004/gallery/master/Rokuonji/舍利殿-镜湖池全景.webp", "url": "https://xiaolin2004.github.io/gallery?name=Rokuonji/舍利殿-镜湖池全景.webp", "external_url": "https://xiaolin2004.github.io/gallery?name=Rokuonji/舍利殿-镜湖池全景.webp", "title": "舍利殿-镜湖池全景", "content_html": "<div><img src=\"https://raw.githubusercontent.com/xiaolin2004/gallery/master/Rokuonji/舍利殿-镜湖池全景.webp\"/><p> - · - </p></div>", "image": "https://raw.githubusercontent.com/xiaolin2004/gallery/master/Rokuonji/舍利殿-镜湖池全景.webp", "date_published": "2025-01-01 09:34:07", "date_modified": "2025-01-01 09:34:07"}, {"id": "https://raw.githubusercontent.com/xiaolin2004/gallery/master/Rokuonji/舍利殿倒影.webp", "url": "https://xiaolin2004.github.io/gallery?name=Rokuonji/舍利殿倒影.webp", "external_url": "https://xiaolin2004.github.io/gallery?name=Rokuonji/舍利殿倒影.webp", "title": "舍利殿倒影", "content_html": "<div><img src=\"https://raw.githubusercontent.com/xiaolin2004/gallery/master/Rokuonji/舍利殿倒影.webp\"/><p> - · - </p></div>", "image": "https://raw.githubusercontent.com/xiaolin2004/gallery/master/Rokuonji/舍利殿倒影.webp", "date_published": "2025-01-01 09:29:40", "date_modified": "2025-01-01 09:29:40"}, {"id": "https://raw.githubusercontent.com/xiaolin2004/gallery/master/Rokuonji/镜湖池松树.webp", "url": "https://xiaolin2004.github.io/gallery?name=Rokuonji/镜湖池松树.webp", "external_url": "https://xiaolin2004.github.io/gallery?name=Rokuonji/镜湖池松树.webp", "title": "镜湖池松树", "content_html": "<div><img src=\"https://raw.githubusercontent.com/xiaolin2004/gallery/master/Rokuonji/镜湖池松树.webp\"/><p> - · - </p></div>", "image": "https://raw.githubusercontent.com/xiaolin2004/gallery/master/Rokuonji/镜湖池松树.webp", "date_published": "2025-01-01 09:29:09", "date_modified": "2025-01-01 09:29:09"}, {"id": "https://raw.githubusercontent.com/xiaolin2004/gallery/master/Rokuonji/舍利殿-远眺.webp", "url": "https://xiaolin2004.github.io/gallery?name=Rokuonji/舍利殿-远眺.webp", "external_url": "https://xiaolin2004.github.io/gallery?name=Rokuonji/舍利殿-远眺.webp", "title": "舍利殿-远眺", "content_html": "<div><img src=\"https://raw.githubusercontent.com/xiaolin2004/gallery/master/Rokuonji/舍利殿-远眺.webp\"/><p> - · - </p></div>", "image": "https://raw.githubusercontent.com/xiaolin2004/gallery/master/Rokuonji/舍利殿-远眺.webp", "date_published": "2025-01-01 09:28:21", "date_modified": "2025-01-01 09:28:21"}, {"id": "https://raw.githubusercontent.com/xiaolin2004/gallery/master/GuangzhouZoo/DSC_1288-20241207_455.16m33u8uj0tc.webp", "url": "https://xiaolin2004.github.io/gallery?name=GuangzhouZoo/DSC_1288-20241207_455.16m33u8uj0tc.webp", "external_url": "https://xiaolin2004.github.io/gallery?name=GuangzhouZoo/DSC_1288-20241207_455.16m33u8uj0tc.webp", "title": "DSC_1288-20241207_455.16m33u8uj0tc", "content_html": "<div><img src=\"https://raw.githubusercontent.com/xiaolin2004/gallery/master/GuangzhouZoo/DSC_1288-20241207_455.16m33u8uj0tc.webp\"/><p> - · - </p></div>", "image": "https://raw.githubusercontent.com/xiaolin2004/gallery/master/GuangzhouZoo/DSC_1288-20241207_455.16m33u8uj0tc.webp", "date_published": "2024-12-07 17:43:06", "date_modified": "2024-12-07 17:43:06"}, {"id": "https://raw.githubusercontent.com/xiaolin2004/gallery/master/GuangzhouZoo/DSC_1284-20241207_454.2g7z1qpt42vw.webp", "url": "https://xiaolin2004.github.io/gallery?name=GuangzhouZoo/DSC_1284-20241207_454.2g7z1qpt42vw.webp", "external_url": "https://xiaolin2004.github.io/gallery?name=GuangzhouZoo/DSC_1284-20241207_454.2g7z1qpt42vw.webp", "title": "DSC_1284-20241207_454.2g7z1qpt42vw", "content_html": "<div><img src=\"https://raw.githubusercontent.com/xiaolin2004/gallery/master/GuangzhouZoo/DSC_1284-20241207_454.2g7z1qpt42vw.webp\"/><p> - · - </p></div>", "image": "https://raw.githubusercontent.com/xiaolin2004/gallery/master/GuangzhouZoo/DSC_1284-20241207_454.2g7z1qpt42vw.webp", "date_published": "2024-12-07 17:40:51", "date_modified": "2024-12-07 17:40:51"}, {"id": "https://raw.githubusercontent.com/xiaolin2004/gallery/master/GuangzhouZoo/DSC_1269-20241207_452.3muc68fxqr40.webp", "url": "https://xiaolin2004.github.io/gallery?name=GuangzhouZoo/DSC_1269-20241207_452.3muc68fxqr40.webp", "external_url": "https://xiaolin2004.github.io/gallery?name=GuangzhouZoo/DSC_1269-20241207_452.3muc68fxqr40.webp", "title": "DSC_1269-20241207_452.3muc68fxqr40", "content_html": "<div><img src=\"https://raw.githubusercontent.com/xiaolin2004/gallery/master/GuangzhouZoo/DSC_1269-20241207_452.3muc68fxqr40.webp\"/><p> - · - </p></div>", "image": "https://raw.githubusercontent.com/xiaolin2004/gallery/master/GuangzhouZoo/DSC_1269-20241207_452.3muc68fxqr40.webp", "date_published": "2024-12-07 17:32:03", "date_modified": "2024-12-07 17:32:03"}, {"id": "https://raw.githubusercontent.com/xiaolin2004/gallery/master/GuangzhouZoo/DSC_1270-20241207_453.4qjxqdnb15e0.webp", "url": "https://xiaolin2004.github.io/gallery?name=GuangzhouZoo/DSC_1270-20241207_453.4qjxqdnb15e0.webp", "external_url": "https://xiaolin2004.github.io/gallery?name=GuangzhouZoo/DSC_1270-20241207_453.4qjxqdnb15e0.webp", "title": "DSC_1270-20241207_453.4qjxqdnb15e0", "content_html": "<div><img src=\"https://raw.githubusercontent.com/xiaolin2004/gallery/master/GuangzhouZoo/DSC_1270-20241207_453.4qjxqdnb15e0.webp\"/><p> - · - </p></div>", "image": "https://raw.githubusercontent.com/xiaolin2004/gallery/master/GuangzhouZoo/DSC_1270-20241207_453.4qjxqdnb15e0.webp", "date_published": "2024-12-07 17:32:03", "date_modified": "2024-12-07 17:32:03"}, {"id": "https://raw.githubusercontent.com/xiaolin2004/gallery/master/GuangzhouZoo/DSC_1264-20241207_451.2htdlzqqz2e0.webp", "url": "https://xiaolin2004.github.io/gallery?name=GuangzhouZoo/DSC_1264-20241207_451.2htdlzqqz2e0.webp", "external_url": "https://xiaolin2004.github.io/gallery?name=GuangzhouZoo/DSC_1264-20241207_451.2htdlzqqz2e0.webp", "title": "DSC_1264-20241207_451.2htdlzqqz2e0", "content_html": "<div><img src=\"https://raw.githubusercontent.com/xiaolin2004/gallery/master/GuangzhouZoo/DSC_1264-20241207_451.2htdlzqqz2e0.webp\"/><p> - · - </p></div>", "image": "https://raw.githubusercontent.com/xiaolin2004/gallery/master/GuangzhouZoo/DSC_1264-20241207_451.2htdlzqqz2e0.webp", "date_published": "2024-12-07 17:31:41", "date_modified": "2024-12-07 17:31:41"}, {"id": "https://raw.githubusercontent.com/xiaolin2004/gallery/master/GuangzhouZoo/DSC_1263-20241207_450.2okz7iub3pw0.webp", "url": "https://xiaolin2004.github.io/gallery?name=GuangzhouZoo/DSC_1263-20241207_450.2okz7iub3pw0.webp", "external_url": "https://xiaolin2004.github.io/gallery?name=GuangzhouZoo/DSC_1263-20241207_450.2okz7iub3pw0.webp", "title": "DSC_1263-20241207_450.2okz7iub3pw0", "content_html": "<div><img src=\"https://raw.githubusercontent.com/xiaolin2004/gallery/master/GuangzhouZoo/DSC_1263-20241207_450.2okz7iub3pw0.webp\"/><p> - · - </p></div>", "image": "https://raw.githubusercontent.com/xiaolin2004/gallery/master/GuangzhouZoo/DSC_1263-20241207_450.2okz7iub3pw0.webp", "date_published": "2024-12-07 17:31:34", "date_modified": "2024-12-07 17:31:34"}, {"id": "https://raw.githubusercontent.com/xiaolin2004/gallery/master/GuangzhouZoo/DSC_1259-20241207_449.65q3lp4edo00.webp", "url": "https://xiaolin2004.github.io/gallery?name=GuangzhouZoo/DSC_1259-20241207_449.65q3lp4edo00.webp", "external_url": "https://xiaolin2004.github.io/gallery?name=GuangzhouZoo/DSC_1259-20241207_449.65q3lp4edo00.webp", "title": "DSC_1259-20241207_449.65q3lp4edo00", "content_html": "<div><img src=\"https://raw.githubusercontent.com/xiaolin2004/gallery/master/GuangzhouZoo/DSC_1259-20241207_449.65q3lp4edo00.webp\"/><p> - · - </p></div>", "image": "https://raw.githubusercontent.com/xiaolin2004/gallery/master/GuangzhouZoo/DSC_1259-20241207_449.65q3lp4edo00.webp", "date_published": "2024-12-07 17:27:37", "date_modified": "2024-12-07 17:27:37"}, {"id": "https://raw.githubusercontent.com/xiaolin2004/gallery/master/GuangzhouZoo/DSC_1256-20241207_448.7fmbqkxmrn80.webp", "url": "https://xiaolin2004.github.io/gallery?name=GuangzhouZoo/DSC_1256-20241207_448.7fmbqkxmrn80.webp", "external_url": "https://xiaolin2004.github.io/gallery?name=GuangzhouZoo/DSC_1256-20241207_448.7fmbqkxmrn80.webp", "title": "DSC_1256-20241207_448.7fmbqkxmrn80", "content_html": "<div><img src=\"https://raw.githubusercontent.com/xiaolin2004/gallery/master/GuangzhouZoo/DSC_1256-20241207_448.7fmbqkxmrn80.webp\"/><p> - · - </p></div>", "image": "https://raw.githubusercontent.com/xiaolin2004/gallery/master/GuangzhouZoo/DSC_1256-20241207_448.7fmbqkxmrn80.webp", "date_published": "2024-12-07 17:27:17", "date_modified": "2024-12-07 17:27:17"}, {"id": "https://raw.githubusercontent.com/xiaolin2004/gallery/master/GuangzhouZoo/DSC_1254-20241207_447.a3uapzqlcig.webp", "url": "https://xiaolin2004.github.io/gallery?name=GuangzhouZoo/DSC_1254-20241207_447.a3uapzqlcig.webp", "external_url": "https://xiaolin2004.github.io/gallery?name=GuangzhouZoo/DSC_1254-20241207_447.a3uapzqlcig.webp", "title": "DSC_1254-20241207_447.a3uapzqlcig", "content_html": "<div><img src=\"https://raw.githubusercontent.com/xiaolin2004/gallery/master/GuangzhouZoo/DSC_1254-20241207_447.a3uapzqlcig.webp\"/><p> - · - </p></div>", "image": "https://raw.githubusercontent.com/xiaolin2004/gallery/master/GuangzhouZoo/DSC_1254-20241207_447.a3uapzqlcig.webp", "date_published": "2024-12-07 17:25:25", "date_modified": "2024-12-07 17:25:25"}, {"id": "https://raw.githubusercontent.com/xiaolin2004/gallery/master/GuangzhouZoo/DSC_1248-20241207_446.56st9wxkhao0.webp", "url": "https://xiaolin2004.github.io/gallery?name=GuangzhouZoo/DSC_1248-20241207_446.56st9wxkhao0.webp", "external_url": "https://xiaolin2004.github.io/gallery?name=GuangzhouZoo/DSC_1248-20241207_446.56st9wxkhao0.webp", "title": "DSC_1248-20241207_446.56st9wxkhao0", "content_html": "<div><img src=\"https://raw.githubusercontent.com/xiaolin2004/gallery/master/GuangzhouZoo/DSC_1248-20241207_446.56st9wxkhao0.webp\"/><p> - · - </p></div>", "image": "https://raw.githubusercontent.com/xiaolin2004/gallery/master/GuangzhouZoo/DSC_1248-20241207_446.56st9wxkhao0.webp", "date_published": "2024-12-07 17:22:50", "date_modified": "2024-12-07 17:22:50"}, {"id": "https://raw.githubusercontent.com/xiaolin2004/gallery/master/GuangzhouZoo/DSC_1247-20241207_445.5j97uw48ivk0.webp", "url": "https://xiaolin2004.github.io/gallery?name=GuangzhouZoo/DSC_1247-20241207_445.5j97uw48ivk0.webp", "external_url": "https://xiaolin2004.github.io/gallery?name=GuangzhouZoo/DSC_1247-20241207_445.5j97uw48ivk0.webp", "title": "DSC_1247-20241207_445.5j97uw48ivk0", "content_html": "<div><img src=\"https://raw.githubusercontent.com/xiaolin2004/gallery/master/GuangzhouZoo/DSC_1247-20241207_445.5j97uw48ivk0.webp\"/><p> - · - </p></div>", "image": "https://raw.githubusercontent.com/xiaolin2004/gallery/master/GuangzhouZoo/DSC_1247-20241207_445.5j97uw48ivk0.webp", "date_published": "2024-12-07 17:22:04", "date_modified": "2024-12-07 17:22:04"}, {"id": "https://raw.githubusercontent.com/xiaolin2004/gallery/master/GuangzhouZoo/DSC_1245-20241207_444.715g94fcajc0.webp", "url": "https://xiaolin2004.github.io/gallery?name=GuangzhouZoo/DSC_1245-20241207_444.715g94fcajc0.webp", "external_url": "https://xiaolin2004.github.io/gallery?name=GuangzhouZoo/DSC_1245-20241207_444.715g94fcajc0.webp", "title": "DSC_1245-20241207_444.715g94fcajc0", "content_html": "<div><img src=\"https://raw.githubusercontent.com/xiaolin2004/gallery/master/GuangzhouZoo/DSC_1245-20241207_444.715g94fcajc0.webp\"/><p> - · - </p></div>", "image": "https://raw.githubusercontent.com/xiaolin2004/gallery/master/GuangzhouZoo/DSC_1245-20241207_444.715g94fcajc0.webp", "date_published": "2024-12-07 17:21:36", "date_modified": "2024-12-07 17:21:36"}, {"id": "https://raw.githubusercontent.com/xiaolin2004/gallery/master/GuangzhouZoo/DSC_1234-20241207_443.42ggw0dlmh00.webp", "url": "https://xiaolin2004.github.io/gallery?name=GuangzhouZoo/DSC_1234-20241207_443.42ggw0dlmh00.webp", "external_url": "https://xiaolin2004.github.io/gallery?name=GuangzhouZoo/DSC_1234-20241207_443.42ggw0dlmh00.webp", "title": "DSC_1234-20241207_443.42ggw0dlmh00", "content_html": "<div><img src=\"https://raw.githubusercontent.com/xiaolin2004/gallery/master/GuangzhouZoo/DSC_1234-20241207_443.42ggw0dlmh00.webp\"/><p> - · - </p></div>", "image": "https://raw.githubusercontent.com/xiaolin2004/gallery/master/GuangzhouZoo/DSC_1234-20241207_443.42ggw0dlmh00.webp", "date_published": "2024-12-07 17:18:51", "date_modified": "2024-12-07 17:18:51"}, {"id": "https://raw.githubusercontent.com/xiaolin2004/gallery/master/GuangzhouZoo/DSC_1230-20241207_442.5i7i8ieo6zc0.webp", "url": "https://xiaolin2004.github.io/gallery?name=GuangzhouZoo/DSC_1230-20241207_442.5i7i8ieo6zc0.webp", "external_url": "https://xiaolin2004.github.io/gallery?name=GuangzhouZoo/DSC_1230-20241207_442.5i7i8ieo6zc0.webp", "title": "DSC_1230-20241207_442.5i7i8ieo6zc0", "content_html": "<div><img src=\"https://raw.githubusercontent.com/xiaolin2004/gallery/master/GuangzhouZoo/DSC_1230-20241207_442.5i7i8ieo6zc0.webp\"/><p> - · - </p></div>", "image": "https://raw.githubusercontent.com/xiaolin2004/gallery/master/GuangzhouZoo/DSC_1230-20241207_442.5i7i8ieo6zc0.webp", "date_published": "2024-12-07 17:17:37", "date_modified": "2024-12-07 17:17:37"}, {"id": "https://raw.githubusercontent.com/xiaolin2004/gallery/master/GuangzhouZoo/DSC_1225-20241207_440.2r2l6j1th18.webp", "url": "https://xiaolin2004.github.io/gallery?name=GuangzhouZoo/DSC_1225-20241207_440.2r2l6j1th18.webp", "external_url": "https://xiaolin2004.github.io/gallery?name=GuangzhouZoo/DSC_1225-20241207_440.2r2l6j1th18.webp", "title": "DSC_1225-20241207_440.2r2l6j1th18", "content_html": "<div><img src=\"https://raw.githubusercontent.com/xiaolin2004/gallery/master/GuangzhouZoo/DSC_1225-20241207_440.2r2l6j1th18.webp\"/><p> - · - </p></div>", "image": "https://raw.githubusercontent.com/xiaolin2004/gallery/master/GuangzhouZoo/DSC_1225-20241207_440.2r2l6j1th18.webp", "date_published": "2024-12-07 17:16:57", "date_modified": "2024-12-07 17:16:57"}, {"id": "https://raw.githubusercontent.com/xiaolin2004/gallery/master/GuangzhouZoo/DSC_1226-20241207_441.27ircegez340.webp", "url": "https://xiaolin2004.github.io/gallery?name=GuangzhouZoo/DSC_1226-20241207_441.27ircegez340.webp", "external_url": "https://xiaolin2004.github.io/gallery?name=GuangzhouZoo/DSC_1226-20241207_441.27ircegez340.webp", "title": "DSC_1226-20241207_441.27ircegez340", "content_html": "<div><img src=\"https://raw.githubusercontent.com/xiaolin2004/gallery/master/GuangzhouZoo/DSC_1226-20241207_441.27ircegez340.webp\"/><p> - · - </p></div>", "image": "https://raw.githubusercontent.com/xiaolin2004/gallery/master/GuangzhouZoo/DSC_1226-20241207_441.27ircegez340.webp", "date_published": "2024-12-07 17:16:57", "date_modified": "2024-12-07 17:16:57"}, {"id": "https://raw.githubusercontent.com/xiaolin2004/gallery/master/GuangzhouZoo/DSC_1224-20241207_439.1tl6mdimsrk0.webp", "url": "https://xiaolin2004.github.io/gallery?name=GuangzhouZoo/DSC_1224-20241207_439.1tl6mdimsrk0.webp", "external_url": "https://xiaolin2004.github.io/gallery?name=GuangzhouZoo/DSC_1224-20241207_439.1tl6mdimsrk0.webp", "title": "DSC_1224-20241207_439.1tl6mdimsrk0", "content_html": "<div><img src=\"https://raw.githubusercontent.com/xiaolin2004/gallery/master/GuangzhouZoo/DSC_1224-20241207_439.1tl6mdimsrk0.webp\"/><p> - · - </p></div>", "image": "https://raw.githubusercontent.com/xiaolin2004/gallery/master/GuangzhouZoo/DSC_1224-20241207_439.1tl6mdimsrk0.webp", "date_published": "2024-12-07 17:16:53", "date_modified": "2024-12-07 17:16:53"}, {"id": "https://raw.githubusercontent.com/xiaolin2004/gallery/master/GuangzhouZoo/DSC_1212-20241207_438.6on2ryic3g40.webp", "url": "https://xiaolin2004.github.io/gallery?name=GuangzhouZoo/DSC_1212-20241207_438.6on2ryic3g40.webp", "external_url": "https://xiaolin2004.github.io/gallery?name=GuangzhouZoo/DSC_1212-20241207_438.6on2ryic3g40.webp", "title": "DSC_1212-20241207_438.6on2ryic3g40", "content_html": "<div><img src=\"https://raw.githubusercontent.com/xiaolin2004/gallery/master/GuangzhouZoo/DSC_1212-20241207_438.6on2ryic3g40.webp\"/><p> - · - </p></div>", "image": "https://raw.githubusercontent.com/xiaolin2004/gallery/master/GuangzhouZoo/DSC_1212-20241207_438.6on2ryic3g40.webp", "date_published": "2024-12-07 17:15:37", "date_modified": "2024-12-07 17:15:37"}, {"id": "https://raw.githubusercontent.com/xiaolin2004/gallery/master/GuangzhouZoo/DSC_1210-20241207_437.70kh8bxn9gw0.webp", "url": "https://xiaolin2004.github.io/gallery?name=GuangzhouZoo/DSC_1210-20241207_437.70kh8bxn9gw0.webp", "external_url": "https://xiaolin2004.github.io/gallery?name=GuangzhouZoo/DSC_1210-20241207_437.70kh8bxn9gw0.webp", "title": "DSC_1210-20241207_437.70kh8bxn9gw0", "content_html": "<div><img src=\"https://raw.githubusercontent.com/xiaolin2004/gallery/master/GuangzhouZoo/DSC_1210-20241207_437.70kh8bxn9gw0.webp\"/><p> - · - </p></div>", "image": "https://raw.githubusercontent.com/xiaolin2004/gallery/master/GuangzhouZoo/DSC_1210-20241207_437.70kh8bxn9gw0.webp", "date_published": "2024-12-07 17:15:29", "date_modified": "2024-12-07 17:15:29"}, {"id": "https://raw.githubusercontent.com/xiaolin2004/gallery/master/GuangzhouZoo/DSC_1200-20241207_436.184n5x15dgq.webp", "url": "https://xiaolin2004.github.io/gallery?name=GuangzhouZoo/DSC_1200-20241207_436.184n5x15dgq.webp", "external_url": "https://xiaolin2004.github.io/gallery?name=GuangzhouZoo/DSC_1200-20241207_436.184n5x15dgq.webp", "title": "DSC_1200-20241207_436.184n5x15dgq", "content_html": "<div><img src=\"https://raw.githubusercontent.com/xiaolin2004/gallery/master/GuangzhouZoo/DSC_1200-20241207_436.184n5x15dgq.webp\"/><p> - · - </p></div>", "image": "https://raw.githubusercontent.com/xiaolin2004/gallery/master/GuangzhouZoo/DSC_1200-20241207_436.184n5x15dgq.webp", "date_published": "2024-12-07 17:13:38", "date_modified": "2024-12-07 17:13:38"}, {"id": "https://raw.githubusercontent.com/xiaolin2004/gallery/master/GuangzhouZoo/DSC_1199-20241207_435.79gvp5kdcyw0.webp", "url": "https://xiaolin2004.github.io/gallery?name=GuangzhouZoo/DSC_1199-20241207_435.79gvp5kdcyw0.webp", "external_url": "https://xiaolin2004.github.io/gallery?name=GuangzhouZoo/DSC_1199-20241207_435.79gvp5kdcyw0.webp", "title": "DSC_1199-20241207_435.79gvp5kdcyw0", "content_html": "<div><img src=\"https://raw.githubusercontent.com/xiaolin2004/gallery/master/GuangzhouZoo/DSC_1199-20241207_435.79gvp5kdcyw0.webp\"/><p> - · - </p></div>", "image": "https://raw.githubusercontent.com/xiaolin2004/gallery/master/GuangzhouZoo/DSC_1199-20241207_435.79gvp5kdcyw0.webp", "date_published": "2024-12-07 17:13:34", "date_modified": "2024-12-07 17:13:34"}, {"id": "https://raw.githubusercontent.com/xiaolin2004/gallery/master/GuangzhouZoo/DSC_1197-20241207_434.2kh6lw19th20.webp", "url": "https://xiaolin2004.github.io/gallery?name=GuangzhouZoo/DSC_1197-20241207_434.2kh6lw19th20.webp", "external_url": "https://xiaolin2004.github.io/gallery?name=GuangzhouZoo/DSC_1197-20241207_434.2kh6lw19th20.webp", "title": "DSC_1197-20241207_434.2kh6lw19th20", "content_html": "<div><img src=\"https://raw.githubusercontent.com/xiaolin2004/gallery/master/GuangzhouZoo/DSC_1197-20241207_434.2kh6lw19th20.webp\"/><p> - · - </p></div>", "image": "https://raw.githubusercontent.com/xiaolin2004/gallery/master/GuangzhouZoo/DSC_1197-20241207_434.2kh6lw19th20.webp", "date_published": "2024-12-07 17:13:23", "date_modified": "2024-12-07 17:13:23"}, {"id": "https://raw.githubusercontent.com/xiaolin2004/gallery/master/GuangzhouZoo/DSC_1196-20241207_433.1w3rqz65u6ao.webp", "url": "https://xiaolin2004.github.io/gallery?name=GuangzhouZoo/DSC_1196-20241207_433.1w3rqz65u6ao.webp", "external_url": "https://xiaolin2004.github.io/gallery?name=GuangzhouZoo/DSC_1196-20241207_433.1w3rqz65u6ao.webp", "title": "DSC_1196-20241207_433.1w3rqz65u6ao", "content_html": "<div><img src=\"https://raw.githubusercontent.com/xiaolin2004/gallery/master/GuangzhouZoo/DSC_1196-20241207_433.1w3rqz65u6ao.webp\"/><p> - · - </p></div>", "image": "https://raw.githubusercontent.com/xiaolin2004/gallery/master/GuangzhouZoo/DSC_1196-20241207_433.1w3rqz65u6ao.webp", "date_published": "2024-12-07 17:13:20", "date_modified": "2024-12-07 17:13:20"}, {"id": "https://raw.githubusercontent.com/xiaolin2004/gallery/master/GuangzhouZoo/DSC_1195-20241207_432.23sjwuwb5934.webp", "url": "https://xiaolin2004.github.io/gallery?name=GuangzhouZoo/DSC_1195-20241207_432.23sjwuwb5934.webp", "external_url": "https://xiaolin2004.github.io/gallery?name=GuangzhouZoo/DSC_1195-20241207_432.23sjwuwb5934.webp", "title": "DSC_1195-20241207_432.23sjwuwb5934", "content_html": "<div><img src=\"https://raw.githubusercontent.com/xiaolin2004/gallery/master/GuangzhouZoo/DSC_1195-20241207_432.23sjwuwb5934.webp\"/><p> - · - </p></div>", "image": "https://raw.githubusercontent.com/xiaolin2004/gallery/master/GuangzhouZoo/DSC_1195-20241207_432.23sjwuwb5934.webp", "date_published": "2024-12-07 17:13:11", "date_modified": "2024-12-07 17:13:11"}, {"id": "https://raw.githubusercontent.com/xiaolin2004/gallery/master/GuangzhouZoo/DSC_1194-20241207_431.ezi1sunfxvc.webp", "url": "https://xiaolin2004.github.io/gallery?name=GuangzhouZoo/DSC_1194-20241207_431.ezi1sunfxvc.webp", "external_url": "https://xiaolin2004.github.io/gallery?name=GuangzhouZoo/DSC_1194-20241207_431.ezi1sunfxvc.webp", "title": "DSC_1194-20241207_431.ezi1sunfxvc", "content_html": "<div><img src=\"https://raw.githubusercontent.com/xiaolin2004/gallery/master/GuangzhouZoo/DSC_1194-20241207_431.ezi1sunfxvc.webp\"/><p> - · - </p></div>", "image": "https://raw.githubusercontent.com/xiaolin2004/gallery/master/GuangzhouZoo/DSC_1194-20241207_431.ezi1sunfxvc.webp", "date_published": "2024-12-07 17:12:50", "date_modified": "2024-12-07 17:12:50"}, {"id": "https://raw.githubusercontent.com/xiaolin2004/gallery/master/GuangzhouZoo/DSC_1193-20241207_430.49luqulitoo0.webp", "url": "https://xiaolin2004.github.io/gallery?name=GuangzhouZoo/DSC_1193-20241207_430.49luqulitoo0.webp", "external_url": "https://xiaolin2004.github.io/gallery?name=GuangzhouZoo/DSC_1193-20241207_430.49luqulitoo0.webp", "title": "DSC_1193-20241207_430.49luqulitoo0", "content_html": "<div><img src=\"https://raw.githubusercontent.com/xiaolin2004/gallery/master/GuangzhouZoo/DSC_1193-20241207_430.49luqulitoo0.webp\"/><p> - · - </p></div>", "image": "https://raw.githubusercontent.com/xiaolin2004/gallery/master/GuangzhouZoo/DSC_1193-20241207_430.49luqulitoo0.webp", "date_published": "2024-12-07 17:12:19", "date_modified": "2024-12-07 17:12:19"}, {"id": "https://raw.githubusercontent.com/xiaolin2004/gallery/master/GuangzhouZoo/DSC_1188-20241207_429.1y324596kso0.webp", "url": "https://xiaolin2004.github.io/gallery?name=GuangzhouZoo/DSC_1188-20241207_429.1y324596kso0.webp", "external_url": "https://xiaolin2004.github.io/gallery?name=GuangzhouZoo/DSC_1188-20241207_429.1y324596kso0.webp", "title": "DSC_1188-20241207_429.1y324596kso0", "content_html": "<div><img src=\"https://raw.githubusercontent.com/xiaolin2004/gallery/master/GuangzhouZoo/DSC_1188-20241207_429.1y324596kso0.webp\"/><p> - · - </p></div>", "image": "https://raw.githubusercontent.com/xiaolin2004/gallery/master/GuangzhouZoo/DSC_1188-20241207_429.1y324596kso0.webp", "date_published": "2024-12-07 17:10:07", "date_modified": "2024-12-07 17:10:07"}, {"id": "https://raw.githubusercontent.com/xiaolin2004/gallery/master/GuangzhouZoo/DSC_1185-20241207_428.3hr7bcbox0m.webp", "url": "https://xiaolin2004.github.io/gallery?name=GuangzhouZoo/DSC_1185-20241207_428.3hr7bcbox0m.webp", "external_url": "https://xiaolin2004.github.io/gallery?name=GuangzhouZoo/DSC_1185-20241207_428.3hr7bcbox0m.webp", "title": "DSC_1185-20241207_428.3hr7bcbox0m", "content_html": "<div><img src=\"https://raw.githubusercontent.com/xiaolin2004/gallery/master/GuangzhouZoo/DSC_1185-20241207_428.3hr7bcbox0m.webp\"/><p> - · - </p></div>", "image": "https://raw.githubusercontent.com/xiaolin2004/gallery/master/GuangzhouZoo/DSC_1185-20241207_428.3hr7bcbox0m.webp", "date_published": "2024-12-07 17:08:53", "date_modified": "2024-12-07 17:08:53"}, {"id": "https://raw.githubusercontent.com/xiaolin2004/gallery/master/GuangzhouZoo/DSC_1183-20241207_427.24ogeacktp28.webp", "url": "https://xiaolin2004.github.io/gallery?name=GuangzhouZoo/DSC_1183-20241207_427.24ogeacktp28.webp", "external_url": "https://xiaolin2004.github.io/gallery?name=GuangzhouZoo/DSC_1183-20241207_427.24ogeacktp28.webp", "title": "DSC_1183-20241207_427.24ogeacktp28", "content_html": "<div><img src=\"https://raw.githubusercontent.com/xiaolin2004/gallery/master/GuangzhouZoo/DSC_1183-20241207_427.24ogeacktp28.webp\"/><p> - · - </p></div>", "image": "https://raw.githubusercontent.com/xiaolin2004/gallery/master/GuangzhouZoo/DSC_1183-20241207_427.24ogeacktp28.webp", "date_published": "2024-12-07 17:08:25", "date_modified": "2024-12-07 17:08:25"}, {"id": "https://raw.githubusercontent.com/xiaolin2004/gallery/master/GuangzhouZoo/DSC_1182-20241207_426.1ccuzh2algdc.webp", "url": "https://xiaolin2004.github.io/gallery?name=GuangzhouZoo/DSC_1182-20241207_426.1ccuzh2algdc.webp", "external_url": "https://xiaolin2004.github.io/gallery?name=GuangzhouZoo/DSC_1182-20241207_426.1ccuzh2algdc.webp", "title": "DSC_1182-20241207_426.1ccuzh2algdc", "content_html": "<div><img src=\"https://raw.githubusercontent.com/xiaolin2004/gallery/master/GuangzhouZoo/DSC_1182-20241207_426.1ccuzh2algdc.webp\"/><p> - · - </p></div>", "image": "https://raw.githubusercontent.com/xiaolin2004/gallery/master/GuangzhouZoo/DSC_1182-20241207_426.1ccuzh2algdc.webp", "date_published": "2024-12-07 17:08:17", "date_modified": "2024-12-07 17:08:17"}, {"id": "https://raw.githubusercontent.com/xiaolin2004/gallery/master/GuangzhouZoo/DSC_1180-20241207_425.7enymx2fwb80.webp", "url": "https://xiaolin2004.github.io/gallery?name=GuangzhouZoo/DSC_1180-20241207_425.7enymx2fwb80.webp", "external_url": "https://xiaolin2004.github.io/gallery?name=GuangzhouZoo/DSC_1180-20241207_425.7enymx2fwb80.webp", "title": "DSC_1180-20241207_425.7enymx2fwb80", "content_html": "<div><img src=\"https://raw.githubusercontent.com/xiaolin2004/gallery/master/GuangzhouZoo/DSC_1180-20241207_425.7enymx2fwb80.webp\"/><p> - · - </p></div>", "image": "https://raw.githubusercontent.com/xiaolin2004/gallery/master/GuangzhouZoo/DSC_1180-20241207_425.7enymx2fwb80.webp", "date_published": "2024-12-07 17:07:56", "date_modified": "2024-12-07 17:07:56"}, {"id": "https://raw.githubusercontent.com/xiaolin2004/gallery/master/GuangzhouZoo/DSC_1179-20241207_424.2m4k2bsjtyo0.webp", "url": "https://xiaolin2004.github.io/gallery?name=GuangzhouZoo/DSC_1179-20241207_424.2m4k2bsjtyo0.webp", "external_url": "https://xiaolin2004.github.io/gallery?name=GuangzhouZoo/DSC_1179-20241207_424.2m4k2bsjtyo0.webp", "title": "DSC_1179-20241207_424.2m4k2bsjtyo0", "content_html": "<div><img src=\"https://raw.githubusercontent.com/xiaolin2004/gallery/master/GuangzhouZoo/DSC_1179-20241207_424.2m4k2bsjtyo0.webp\"/><p> - · - </p></div>", "image": "https://raw.githubusercontent.com/xiaolin2004/gallery/master/GuangzhouZoo/DSC_1179-20241207_424.2m4k2bsjtyo0.webp", "date_published": "2024-12-07 17:07:15", "date_modified": "2024-12-07 17:07:15"}, {"id": "https://raw.githubusercontent.com/xiaolin2004/gallery/master/GuangzhouZoo/DSC_1171-20241207_423.bvcmr34j07s.webp", "url": "https://xiaolin2004.github.io/gallery?name=GuangzhouZoo/DSC_1171-20241207_423.bvcmr34j07s.webp", "external_url": "https://xiaolin2004.github.io/gallery?name=GuangzhouZoo/DSC_1171-20241207_423.bvcmr34j07s.webp", "title": "DSC_1171-20241207_423.bvcmr34j07s", "content_html": "<div><img src=\"https://raw.githubusercontent.com/xiaolin2004/gallery/master/GuangzhouZoo/DSC_1171-20241207_423.bvcmr34j07s.webp\"/><p> - · - </p></div>", "image": "https://raw.githubusercontent.com/xiaolin2004/gallery/master/GuangzhouZoo/DSC_1171-20241207_423.bvcmr34j07s.webp", "date_published": "2024-12-07 17:05:50", "date_modified": "2024-12-07 17:05:50"}, {"id": "https://raw.githubusercontent.com/xiaolin2004/gallery/master/GuangzhouZoo/DSC_1168-20241207_422.2btjmarclolc.webp", "url": "https://xiaolin2004.github.io/gallery?name=GuangzhouZoo/DSC_1168-20241207_422.2btjmarclolc.webp", "external_url": "https://xiaolin2004.github.io/gallery?name=GuangzhouZoo/DSC_1168-20241207_422.2btjmarclolc.webp", "title": "DSC_1168-20241207_422.2btjmarclolc", "content_html": "<div><img src=\"https://raw.githubusercontent.com/xiaolin2004/gallery/master/GuangzhouZoo/DSC_1168-20241207_422.2btjmarclolc.webp\"/><p> - · - </p></div>", "image": "https://raw.githubusercontent.com/xiaolin2004/gallery/master/GuangzhouZoo/DSC_1168-20241207_422.2btjmarclolc.webp", "date_published": "2024-12-07 17:05:39", "date_modified": "2024-12-07 17:05:39"}, {"id": "https://raw.githubusercontent.com/xiaolin2004/gallery/master/GuangzhouZoo/DSC_1167-20241207_421.346183e8i4q.webp", "url": "https://xiaolin2004.github.io/gallery?name=GuangzhouZoo/DSC_1167-20241207_421.346183e8i4q.webp", "external_url": "https://xiaolin2004.github.io/gallery?name=GuangzhouZoo/DSC_1167-20241207_421.346183e8i4q.webp", "title": "DSC_1167-20241207_421.346183e8i4q", "content_html": "<div><img src=\"https://raw.githubusercontent.com/xiaolin2004/gallery/master/GuangzhouZoo/DSC_1167-20241207_421.346183e8i4q.webp\"/><p> - · - </p></div>", "image": "https://raw.githubusercontent.com/xiaolin2004/gallery/master/GuangzhouZoo/DSC_1167-20241207_421.346183e8i4q.webp", "date_published": "2024-12-07 17:05:26", "date_modified": "2024-12-07 17:05:26"}, {"id": "https://raw.githubusercontent.com/xiaolin2004/gallery/master/GuangzhouZoo/DSC_1160-20241207_420.gylbr28keqo.webp", "url": "https://xiaolin2004.github.io/gallery?name=GuangzhouZoo/DSC_1160-20241207_420.gylbr28keqo.webp", "external_url": "https://xiaolin2004.github.io/gallery?name=GuangzhouZoo/DSC_1160-20241207_420.gylbr28keqo.webp", "title": "DSC_1160-20241207_420.gylbr28keqo", "content_html": "<div><img src=\"https://raw.githubusercontent.com/xiaolin2004/gallery/master/GuangzhouZoo/DSC_1160-20241207_420.gylbr28keqo.webp\"/><p> - · - </p></div>", "image": "https://raw.githubusercontent.com/xiaolin2004/gallery/master/GuangzhouZoo/DSC_1160-20241207_420.gylbr28keqo.webp", "date_published": "2024-12-07 17:04:23", "date_modified": "2024-12-07 17:04:23"}, {"id": "https://raw.githubusercontent.com/xiaolin2004/gallery/master/GuangzhouZoo/DSC_1143-20241207_419.3ohbg8gcixs0.webp", "url": "https://xiaolin2004.github.io/gallery?name=GuangzhouZoo/DSC_1143-20241207_419.3ohbg8gcixs0.webp", "external_url": "https://xiaolin2004.github.io/gallery?name=GuangzhouZoo/DSC_1143-20241207_419.3ohbg8gcixs0.webp", "title": "DSC_1143-20241207_419.3ohbg8gcixs0", "content_html": "<div><img src=\"https://raw.githubusercontent.com/xiaolin2004/gallery/master/GuangzhouZoo/DSC_1143-20241207_419.3ohbg8gcixs0.webp\"/><p> - · - </p></div>", "image": "https://raw.githubusercontent.com/xiaolin2004/gallery/master/GuangzhouZoo/DSC_1143-20241207_419.3ohbg8gcixs0.webp", "date_published": "2024-12-07 17:01:57", "date_modified": "2024-12-07 17:01:57"}, {"id": "https://raw.githubusercontent.com/xiaolin2004/gallery/master/GuangzhouZoo/DSC_1142-20241207_418.5hpon7vx0bk0.webp", "url": "https://xiaolin2004.github.io/gallery?name=GuangzhouZoo/DSC_1142-20241207_418.5hpon7vx0bk0.webp", "external_url": "https://xiaolin2004.github.io/gallery?name=GuangzhouZoo/DSC_1142-20241207_418.5hpon7vx0bk0.webp", "title": "DSC_1142-20241207_418.5hpon7vx0bk0", "content_html": "<div><img src=\"https://raw.githubusercontent.com/xiaolin2004/gallery/master/GuangzhouZoo/DSC_1142-20241207_418.5hpon7vx0bk0.webp\"/><p> - · - </p></div>", "image": "https://raw.githubusercontent.com/xiaolin2004/gallery/master/GuangzhouZoo/DSC_1142-20241207_418.5hpon7vx0bk0.webp", "date_published": "2024-12-07 17:01:53", "date_modified": "2024-12-07 17:01:53"}, {"id": "https://raw.githubusercontent.com/xiaolin2004/gallery/master/GuangzhouZoo/DSC_1141-20241207_417.4proozrpmyw.webp", "url": "https://xiaolin2004.github.io/gallery?name=GuangzhouZoo/DSC_1141-20241207_417.4proozrpmyw.webp", "external_url": "https://xiaolin2004.github.io/gallery?name=GuangzhouZoo/DSC_1141-20241207_417.4proozrpmyw.webp", "title": "DSC_1141-20241207_417.4proozrpmyw", "content_html": "<div><img src=\"https://raw.githubusercontent.com/xiaolin2004/gallery/master/GuangzhouZoo/DSC_1141-20241207_417.4proozrpmyw.webp\"/><p> - · - </p></div>", "image": "https://raw.githubusercontent.com/xiaolin2004/gallery/master/GuangzhouZoo/DSC_1141-20241207_417.4proozrpmyw.webp", "date_published": "2024-12-07 17:01:45", "date_modified": "2024-12-07 17:01:45"}, {"id": "https://raw.githubusercontent.com/xiaolin2004/gallery/master/GuangzhouZoo/DSC_1140-20241207_416.5zjo46dyw880.webp", "url": "https://xiaolin2004.github.io/gallery?name=GuangzhouZoo/DSC_1140-20241207_416.5zjo46dyw880.webp", "external_url": "https://xiaolin2004.github.io/gallery?name=GuangzhouZoo/DSC_1140-20241207_416.5zjo46dyw880.webp", "title": "DSC_1140-20241207_416.5zjo46dyw880", "content_html": "<div><img src=\"https://raw.githubusercontent.com/xiaolin2004/gallery/master/GuangzhouZoo/DSC_1140-20241207_416.5zjo46dyw880.webp\"/><p> - · - </p></div>", "image": "https://raw.githubusercontent.com/xiaolin2004/gallery/master/GuangzhouZoo/DSC_1140-20241207_416.5zjo46dyw880.webp", "date_published": "2024-12-07 17:01:37", "date_modified": "2024-12-07 17:01:37"}, {"id": "https://raw.githubusercontent.com/xiaolin2004/gallery/master/GuangzhouZoo/DSC_1137-20241207_414.15u4es995l6o.webp", "url": "https://xiaolin2004.github.io/gallery?name=GuangzhouZoo/DSC_1137-20241207_414.15u4es995l6o.webp", "external_url": "https://xiaolin2004.github.io/gallery?name=GuangzhouZoo/DSC_1137-20241207_414.15u4es995l6o.webp", "title": "DSC_1137-20241207_414.15u4es995l6o", "content_html": "<div><img src=\"https://raw.githubusercontent.com/xiaolin2004/gallery/master/GuangzhouZoo/DSC_1137-20241207_414.15u4es995l6o.webp\"/><p> - · - </p></div>", "image": "https://raw.githubusercontent.com/xiaolin2004/gallery/master/GuangzhouZoo/DSC_1137-20241207_414.15u4es995l6o.webp", "date_published": "2024-12-07 17:01:21", "date_modified": "2024-12-07 17:01:21"}, {"id": "https://raw.githubusercontent.com/xiaolin2004/gallery/master/GuangzhouZoo/DSC_1136-20241207_413.3hfh7by8efs0.webp", "url": "https://xiaolin2004.github.io/gallery?name=GuangzhouZoo/DSC_1136-20241207_413.3hfh7by8efs0.webp", "external_url": "https://xiaolin2004.github.io/gallery?name=GuangzhouZoo/DSC_1136-20241207_413.3hfh7by8efs0.webp", "title": "DSC_1136-20241207_413.3hfh7by8efs0", "content_html": "<div><img src=\"https://raw.githubusercontent.com/xiaolin2004/gallery/master/GuangzhouZoo/DSC_1136-20241207_413.3hfh7by8efs0.webp\"/><p> - · - </p></div>", "image": "https://raw.githubusercontent.com/xiaolin2004/gallery/master/GuangzhouZoo/DSC_1136-20241207_413.3hfh7by8efs0.webp", "date_published": "2024-12-07 17:01:15", "date_modified": "2024-12-07 17:01:15"}, {"id": "https://raw.githubusercontent.com/xiaolin2004/gallery/master/GuangzhouZoo/DSC_1130-20241207_412.9j2d5dh6f74.webp", "url": "https://xiaolin2004.github.io/gallery?name=GuangzhouZoo/DSC_1130-20241207_412.9j2d5dh6f74.webp", "external_url": "https://xiaolin2004.github.io/gallery?name=GuangzhouZoo/DSC_1130-20241207_412.9j2d5dh6f74.webp", "title": "DSC_1130-20241207_412.9j2d5dh6f74", "content_html": "<div><img src=\"https://raw.githubusercontent.com/xiaolin2004/gallery/master/GuangzhouZoo/DSC_1130-20241207_412.9j2d5dh6f74.webp\"/><p> - · - </p></div>", "image": "https://raw.githubusercontent.com/xiaolin2004/gallery/master/GuangzhouZoo/DSC_1130-20241207_412.9j2d5dh6f74.webp", "date_published": "2024-12-07 17:00:41", "date_modified": "2024-12-07 17:00:41"}, {"id": "https://raw.githubusercontent.com/xiaolin2004/gallery/master/GuangzhouZoo/DSC_1118-20241207_411.5k9necnhcsc0.webp", "url": "https://xiaolin2004.github.io/gallery?name=GuangzhouZoo/DSC_1118-20241207_411.5k9necnhcsc0.webp", "external_url": "https://xiaolin2004.github.io/gallery?name=GuangzhouZoo/DSC_1118-20241207_411.5k9necnhcsc0.webp", "title": "DSC_1118-20241207_411.5k9necnhcsc0", "content_html": "<div><img src=\"https://raw.githubusercontent.com/xiaolin2004/gallery/master/GuangzhouZoo/DSC_1118-20241207_411.5k9necnhcsc0.webp\"/><p> - · - </p></div>", "image": "https://raw.githubusercontent.com/xiaolin2004/gallery/master/GuangzhouZoo/DSC_1118-20241207_411.5k9necnhcsc0.webp", "date_published": "2024-12-07 16:55:45", "date_modified": "2024-12-07 16:55:45"}, {"id": "https://raw.githubusercontent.com/xiaolin2004/gallery/master/GuangzhouZoo/DSC_1115-20241207_410.5bte9gmbpns0.webp", "url": "https://xiaolin2004.github.io/gallery?name=GuangzhouZoo/DSC_1115-20241207_410.5bte9gmbpns0.webp", "external_url": "https://xiaolin2004.github.io/gallery?name=GuangzhouZoo/DSC_1115-20241207_410.5bte9gmbpns0.webp", "title": "DSC_1115-20241207_410.5bte9gmbpns0", "content_html": "<div><img src=\"https://raw.githubusercontent.com/xiaolin2004/gallery/master/GuangzhouZoo/DSC_1115-20241207_410.5bte9gmbpns0.webp\"/><p> - · - </p></div>", "image": "https://raw.githubusercontent.com/xiaolin2004/gallery/master/GuangzhouZoo/DSC_1115-20241207_410.5bte9gmbpns0.webp", "date_published": "2024-12-07 16:55:44", "date_modified": "2024-12-07 16:55:44"}, {"id": "https://raw.githubusercontent.com/xiaolin2004/gallery/master/GuangzhouZoo/DSC_1107-20241207_409.65o15wgcf2o0.webp", "url": "https://xiaolin2004.github.io/gallery?name=GuangzhouZoo/DSC_1107-20241207_409.65o15wgcf2o0.webp", "external_url": "https://xiaolin2004.github.io/gallery?name=GuangzhouZoo/DSC_1107-20241207_409.65o15wgcf2o0.webp", "title": "DSC_1107-20241207_409.65o15wgcf2o0", "content_html": "<div><img src=\"https://raw.githubusercontent.com/xiaolin2004/gallery/master/GuangzhouZoo/DSC_1107-20241207_409.65o15wgcf2o0.webp\"/><p> - · - </p></div>", "image": "https://raw.githubusercontent.com/xiaolin2004/gallery/master/GuangzhouZoo/DSC_1107-20241207_409.65o15wgcf2o0.webp", "date_published": "2024-12-07 16:54:40", "date_modified": "2024-12-07 16:54:40"}, {"id": "https://raw.githubusercontent.com/xiaolin2004/gallery/master/GuangzhouZoo/DSC_1100-20241207_408.2pe4fw2i61k0.webp", "url": "https://xiaolin2004.github.io/gallery?name=GuangzhouZoo/DSC_1100-20241207_408.2pe4fw2i61k0.webp", "external_url": "https://xiaolin2004.github.io/gallery?name=GuangzhouZoo/DSC_1100-20241207_408.2pe4fw2i61k0.webp", "title": "DSC_1100-20241207_408.2pe4fw2i61k0", "content_html": "<div><img src=\"https://raw.githubusercontent.com/xiaolin2004/gallery/master/GuangzhouZoo/DSC_1100-20241207_408.2pe4fw2i61k0.webp\"/><p> - · - </p></div>", "image": "https://raw.githubusercontent.com/xiaolin2004/gallery/master/GuangzhouZoo/DSC_1100-20241207_408.2pe4fw2i61k0.webp", "date_published": "2024-12-07 16:52:52", "date_modified": "2024-12-07 16:52:52"}, {"id": "https://raw.githubusercontent.com/xiaolin2004/gallery/master/GuangzhouZoo/DSC_1079-20241207_407.6w52csm0obc0.webp", "url": "https://xiaolin2004.github.io/gallery?name=GuangzhouZoo/DSC_1079-20241207_407.6w52csm0obc0.webp", "external_url": "https://xiaolin2004.github.io/gallery?name=GuangzhouZoo/DSC_1079-20241207_407.6w52csm0obc0.webp", "title": "DSC_1079-20241207_407.6w52csm0obc0", "content_html": "<div><img src=\"https://raw.githubusercontent.com/xiaolin2004/gallery/master/GuangzhouZoo/DSC_1079-20241207_407.6w52csm0obc0.webp\"/><p> - · - </p></div>", "image": "https://raw.githubusercontent.com/xiaolin2004/gallery/master/GuangzhouZoo/DSC_1079-20241207_407.6w52csm0obc0.webp", "date_published": "2024-12-07 16:49:54", "date_modified": "2024-12-07 16:49:54"}, {"id": "https://raw.githubusercontent.com/xiaolin2004/gallery/master/GuangzhouZoo/DSC_1071-20241207_406.7cvdb6o62tc0.webp", "url": "https://xiaolin2004.github.io/gallery?name=GuangzhouZoo/DSC_1071-20241207_406.7cvdb6o62tc0.webp", "external_url": "https://xiaolin2004.github.io/gallery?name=GuangzhouZoo/DSC_1071-20241207_406.7cvdb6o62tc0.webp", "title": "DSC_1071-20241207_406.7cvdb6o62tc0", "content_html": "<div><img src=\"https://raw.githubusercontent.com/xiaolin2004/gallery/master/GuangzhouZoo/DSC_1071-20241207_406.7cvdb6o62tc0.webp\"/><p> - · - </p></div>", "image": "https://raw.githubusercontent.com/xiaolin2004/gallery/master/GuangzhouZoo/DSC_1071-20241207_406.7cvdb6o62tc0.webp", "date_published": "2024-12-07 16:46:52", "date_modified": "2024-12-07 16:46:52"}, {"id": "https://raw.githubusercontent.com/xiaolin2004/gallery/master/GuangzhouZoo/DSC_1070-20241207_405.3wl2eqjglhe0.webp", "url": "https://xiaolin2004.github.io/gallery?name=GuangzhouZoo/DSC_1070-20241207_405.3wl2eqjglhe0.webp", "external_url": "https://xiaolin2004.github.io/gallery?name=GuangzhouZoo/DSC_1070-20241207_405.3wl2eqjglhe0.webp", "title": "DSC_1070-20241207_405.3wl2eqjglhe0", "content_html": "<div><img src=\"https://raw.githubusercontent.com/xiaolin2004/gallery/master/GuangzhouZoo/DSC_1070-20241207_405.3wl2eqjglhe0.webp\"/><p> - · - </p></div>", "image": "https://raw.githubusercontent.com/xiaolin2004/gallery/master/GuangzhouZoo/DSC_1070-20241207_405.3wl2eqjglhe0.webp", "date_published": "2024-12-07 16:46:44", "date_modified": "2024-12-07 16:46:44"}, {"id": "https://raw.githubusercontent.com/xiaolin2004/gallery/master/GuangzhouZoo/DSC_1069-20241207_404.5q2zfttkf6k0.webp", "url": "https://xiaolin2004.github.io/gallery?name=GuangzhouZoo/DSC_1069-20241207_404.5q2zfttkf6k0.webp", "external_url": "https://xiaolin2004.github.io/gallery?name=GuangzhouZoo/DSC_1069-20241207_404.5q2zfttkf6k0.webp", "title": "DSC_1069-20241207_404.5q2zfttkf6k0", "content_html": "<div><img src=\"https://raw.githubusercontent.com/xiaolin2004/gallery/master/GuangzhouZoo/DSC_1069-20241207_404.5q2zfttkf6k0.webp\"/><p> - · - </p></div>", "image": "https://raw.githubusercontent.com/xiaolin2004/gallery/master/GuangzhouZoo/DSC_1069-20241207_404.5q2zfttkf6k0.webp", "date_published": "2024-12-07 16:46:41", "date_modified": "2024-12-07 16:46:41"}, {"id": "https://raw.githubusercontent.com/xiaolin2004/gallery/master/GuangzhouZoo/DSC_1067-20241207_403.6i5f6z06jeo0.webp", "url": "https://xiaolin2004.github.io/gallery?name=GuangzhouZoo/DSC_1067-20241207_403.6i5f6z06jeo0.webp", "external_url": "https://xiaolin2004.github.io/gallery?name=GuangzhouZoo/DSC_1067-20241207_403.6i5f6z06jeo0.webp", "title": "DSC_1067-20241207_403.6i5f6z06jeo0", "content_html": "<div><img src=\"https://raw.githubusercontent.com/xiaolin2004/gallery/master/GuangzhouZoo/DSC_1067-20241207_403.6i5f6z06jeo0.webp\"/><p> - · - </p></div>", "image": "https://raw.githubusercontent.com/xiaolin2004/gallery/master/GuangzhouZoo/DSC_1067-20241207_403.6i5f6z06jeo0.webp", "date_published": "2024-12-07 16:46:35", "date_modified": "2024-12-07 16:46:35"}, {"id": "https://raw.githubusercontent.com/xiaolin2004/gallery/master/GuangzhouZoo/DSC_1059-20241207_402.3w5460tbr9c0.webp", "url": "https://xiaolin2004.github.io/gallery?name=GuangzhouZoo/DSC_1059-20241207_402.3w5460tbr9c0.webp", "external_url": "https://xiaolin2004.github.io/gallery?name=GuangzhouZoo/DSC_1059-20241207_402.3w5460tbr9c0.webp", "title": "DSC_1059-20241207_402.3w5460tbr9c0", "content_html": "<div><img src=\"https://raw.githubusercontent.com/xiaolin2004/gallery/master/GuangzhouZoo/DSC_1059-20241207_402.3w5460tbr9c0.webp\"/><p> - · - </p></div>", "image": "https://raw.githubusercontent.com/xiaolin2004/gallery/master/GuangzhouZoo/DSC_1059-20241207_402.3w5460tbr9c0.webp", "date_published": "2024-12-07 16:44:59", "date_modified": "2024-12-07 16:44:59"}, {"id": "https://raw.githubusercontent.com/xiaolin2004/gallery/master/GuangzhouZoo/DSC_1057-20241207_401.4mipal6wquw0.webp", "url": "https://xiaolin2004.github.io/gallery?name=GuangzhouZoo/DSC_1057-20241207_401.4mipal6wquw0.webp", "external_url": "https://xiaolin2004.github.io/gallery?name=GuangzhouZoo/DSC_1057-20241207_401.4mipal6wquw0.webp", "title": "DSC_1057-20241207_401.4mipal6wquw0", "content_html": "<div><img src=\"https://raw.githubusercontent.com/xiaolin2004/gallery/master/GuangzhouZoo/DSC_1057-20241207_401.4mipal6wquw0.webp\"/><p> - · - </p></div>", "image": "https://raw.githubusercontent.com/xiaolin2004/gallery/master/GuangzhouZoo/DSC_1057-20241207_401.4mipal6wquw0.webp", "date_published": "2024-12-07 16:44:43", "date_modified": "2024-12-07 16:44:43"}, {"id": "https://raw.githubusercontent.com/xiaolin2004/gallery/master/GuangzhouZoo/DSC_1056-20241207_400.46uwbgc24uu0.webp", "url": "https://xiaolin2004.github.io/gallery?name=GuangzhouZoo/DSC_1056-20241207_400.46uwbgc24uu0.webp", "external_url": "https://xiaolin2004.github.io/gallery?name=GuangzhouZoo/DSC_1056-20241207_400.46uwbgc24uu0.webp", "title": "DSC_1056-20241207_400.46uwbgc24uu0", "content_html": "<div><img src=\"https://raw.githubusercontent.com/xiaolin2004/gallery/master/GuangzhouZoo/DSC_1056-20241207_400.46uwbgc24uu0.webp\"/><p> - · - </p></div>", "image": "https://raw.githubusercontent.com/xiaolin2004/gallery/master/GuangzhouZoo/DSC_1056-20241207_400.46uwbgc24uu0.webp", "date_published": "2024-12-07 16:44:31", "date_modified": "2024-12-07 16:44:31"}, {"id": "https://raw.githubusercontent.com/xiaolin2004/gallery/master/GuangzhouZoo/DSC_1047-20241207_399.16d82zybu800.webp", "url": "https://xiaolin2004.github.io/gallery?name=GuangzhouZoo/DSC_1047-20241207_399.16d82zybu800.webp", "external_url": "https://xiaolin2004.github.io/gallery?name=GuangzhouZoo/DSC_1047-20241207_399.16d82zybu800.webp", "title": "DSC_1047-20241207_399.16d82zybu800", "content_html": "<div><img src=\"https://raw.githubusercontent.com/xiaolin2004/gallery/master/GuangzhouZoo/DSC_1047-20241207_399.16d82zybu800.webp\"/><p> - · - </p></div>", "image": "https://raw.githubusercontent.com/xiaolin2004/gallery/master/GuangzhouZoo/DSC_1047-20241207_399.16d82zybu800.webp", "date_published": "2024-12-07 16:42:11", "date_modified": "2024-12-07 16:42:11"}, {"id": "https://raw.githubusercontent.com/xiaolin2004/gallery/master/GuangzhouZoo/DSC_1042-20241207_398.4a3yyyxffk60.webp", "url": "https://xiaolin2004.github.io/gallery?name=GuangzhouZoo/DSC_1042-20241207_398.4a3yyyxffk60.webp", "external_url": "https://xiaolin2004.github.io/gallery?name=GuangzhouZoo/DSC_1042-20241207_398.4a3yyyxffk60.webp", "title": "DSC_1042-20241207_398.4a3yyyxffk60", "content_html": "<div><img src=\"https://raw.githubusercontent.com/xiaolin2004/gallery/master/GuangzhouZoo/DSC_1042-20241207_398.4a3yyyxffk60.webp\"/><p> - · - </p></div>", "image": "https://raw.githubusercontent.com/xiaolin2004/gallery/master/GuangzhouZoo/DSC_1042-20241207_398.4a3yyyxffk60.webp", "date_published": "2024-12-07 16:38:32", "date_modified": "2024-12-07 16:38:32"}, {"id": "https://raw.githubusercontent.com/xiaolin2004/gallery/master/GuangzhouZoo/DSC_1040-20241207_396.5fnfxrpe1fk0.webp", "url": "https://xiaolin2004.github.io/gallery?name=GuangzhouZoo/DSC_1040-20241207_396.5fnfxrpe1fk0.webp", "external_url": "https://xiaolin2004.github.io/gallery?name=GuangzhouZoo/DSC_1040-20241207_396.5fnfxrpe1fk0.webp", "title": "DSC_1040-20241207_396.5fnfxrpe1fk0", "content_html": "<div><img src=\"https://raw.githubusercontent.com/xiaolin2004/gallery/master/GuangzhouZoo/DSC_1040-20241207_396.5fnfxrpe1fk0.webp\"/><p> - · - </p></div>", "image": "https://raw.githubusercontent.com/xiaolin2004/gallery/master/GuangzhouZoo/DSC_1040-20241207_396.5fnfxrpe1fk0.webp", "date_published": "2024-12-07 16:38:22", "date_modified": "2024-12-07 16:38:22"}, {"id": "https://raw.githubusercontent.com/xiaolin2004/gallery/master/GuangzhouZoo/DSC_1041-20241207_397.4llwwob6sqg0.webp", "url": "https://xiaolin2004.github.io/gallery?name=GuangzhouZoo/DSC_1041-20241207_397.4llwwob6sqg0.webp", "external_url": "https://xiaolin2004.github.io/gallery?name=GuangzhouZoo/DSC_1041-20241207_397.4llwwob6sqg0.webp", "title": "DSC_1041-20241207_397.4llwwob6sqg0", "content_html": "<div><img src=\"https://raw.githubusercontent.com/xiaolin2004/gallery/master/GuangzhouZoo/DSC_1041-20241207_397.4llwwob6sqg0.webp\"/><p> - · - </p></div>", "image": "https://raw.githubusercontent.com/xiaolin2004/gallery/master/GuangzhouZoo/DSC_1041-20241207_397.4llwwob6sqg0.webp", "date_published": "2024-12-07 16:38:22", "date_modified": "2024-12-07 16:38:22"}, {"id": "https://raw.githubusercontent.com/xiaolin2004/gallery/master/GuangzhouZoo/DSC_1034-20241207_395.3jvlpp6u8yg0.webp", "url": "https://xiaolin2004.github.io/gallery?name=GuangzhouZoo/DSC_1034-20241207_395.3jvlpp6u8yg0.webp", "external_url": "https://xiaolin2004.github.io/gallery?name=GuangzhouZoo/DSC_1034-20241207_395.3jvlpp6u8yg0.webp", "title": "DSC_1034-20241207_395.3jvlpp6u8yg0", "content_html": "<div><img src=\"https://raw.githubusercontent.com/xiaolin2004/gallery/master/GuangzhouZoo/DSC_1034-20241207_395.3jvlpp6u8yg0.webp\"/><p> - · - </p></div>", "image": "https://raw.githubusercontent.com/xiaolin2004/gallery/master/GuangzhouZoo/DSC_1034-20241207_395.3jvlpp6u8yg0.webp", "date_published": "2024-12-07 16:34:41", "date_modified": "2024-12-07 16:34:41"}, {"id": "https://raw.githubusercontent.com/xiaolin2004/gallery/master/GuangzhouZoo/DSC_1029-20241207_394.1ehd7xsb52f4.webp", "url": "https://xiaolin2004.github.io/gallery?name=GuangzhouZoo/DSC_1029-20241207_394.1ehd7xsb52f4.webp", "external_url": "https://xiaolin2004.github.io/gallery?name=GuangzhouZoo/DSC_1029-20241207_394.1ehd7xsb52f4.webp", "title": "DSC_1029-20241207_394.1ehd7xsb52f4", "content_html": "<div><img src=\"https://raw.githubusercontent.com/xiaolin2004/gallery/master/GuangzhouZoo/DSC_1029-20241207_394.1ehd7xsb52f4.webp\"/><p> - · - </p></div>", "image": "https://raw.githubusercontent.com/xiaolin2004/gallery/master/GuangzhouZoo/DSC_1029-20241207_394.1ehd7xsb52f4.webp", "date_published": "2024-12-07 16:34:10", "date_modified": "2024-12-07 16:34:10"}, {"id": "https://raw.githubusercontent.com/xiaolin2004/gallery/master/GuangzhouZoo/DSC_1028-20241207_393.3mfgx80osck0.webp", "url": "https://xiaolin2004.github.io/gallery?name=GuangzhouZoo/DSC_1028-20241207_393.3mfgx80osck0.webp", "external_url": "https://xiaolin2004.github.io/gallery?name=GuangzhouZoo/DSC_1028-20241207_393.3mfgx80osck0.webp", "title": "DSC_1028-20241207_393.3mfgx80osck0", "content_html": "<div><img src=\"https://raw.githubusercontent.com/xiaolin2004/gallery/master/GuangzhouZoo/DSC_1028-20241207_393.3mfgx80osck0.webp\"/><p> - · - </p></div>", "image": "https://raw.githubusercontent.com/xiaolin2004/gallery/master/GuangzhouZoo/DSC_1028-20241207_393.3mfgx80osck0.webp", "date_published": "2024-12-07 16:34:08", "date_modified": "2024-12-07 16:34:08"}, {"id": "https://raw.githubusercontent.com/xiaolin2004/gallery/master/GuangzhouZoo/DSC_1027-20241207_392.126h531sbpls.webp", "url": "https://xiaolin2004.github.io/gallery?name=GuangzhouZoo/DSC_1027-20241207_392.126h531sbpls.webp", "external_url": "https://xiaolin2004.github.io/gallery?name=GuangzhouZoo/DSC_1027-20241207_392.126h531sbpls.webp", "title": "DSC_1027-20241207_392.126h531sbpls", "content_html": "<div><img src=\"https://raw.githubusercontent.com/xiaolin2004/gallery/master/GuangzhouZoo/DSC_1027-20241207_392.126h531sbpls.webp\"/><p> - · - </p></div>", "image": "https://raw.githubusercontent.com/xiaolin2004/gallery/master/GuangzhouZoo/DSC_1027-20241207_392.126h531sbpls.webp", "date_published": "2024-12-07 16:33:39", "date_modified": "2024-12-07 16:33:39"}, {"id": "https://raw.githubusercontent.com/xiaolin2004/gallery/master/GuangzhouZoo/DSC_1025-20241207_391.1ei217cbsleo.webp", "url": "https://xiaolin2004.github.io/gallery?name=GuangzhouZoo/DSC_1025-20241207_391.1ei217cbsleo.webp", "external_url": "https://xiaolin2004.github.io/gallery?name=GuangzhouZoo/DSC_1025-20241207_391.1ei217cbsleo.webp", "title": "DSC_1025-20241207_391.1ei217cbsleo", "content_html": "<div><img src=\"https://raw.githubusercontent.com/xiaolin2004/gallery/master/GuangzhouZoo/DSC_1025-20241207_391.1ei217cbsleo.webp\"/><p> - · - </p></div>", "image": "https://raw.githubusercontent.com/xiaolin2004/gallery/master/GuangzhouZoo/DSC_1025-20241207_391.1ei217cbsleo.webp", "date_published": "2024-12-07 16:32:59", "date_modified": "2024-12-07 16:32:59"}, {"id": "https://raw.githubusercontent.com/xiaolin2004/gallery/master/GuangzhouZoo/DSC_1024-20241207_390.6f168baxte80.webp", "url": "https://xiaolin2004.github.io/gallery?name=GuangzhouZoo/DSC_1024-20241207_390.6f168baxte80.webp", "external_url": "https://xiaolin2004.github.io/gallery?name=GuangzhouZoo/DSC_1024-20241207_390.6f168baxte80.webp", "title": "DSC_1024-20241207_390.6f168baxte80", "content_html": "<div><img src=\"https://raw.githubusercontent.com/xiaolin2004/gallery/master/GuangzhouZoo/DSC_1024-20241207_390.6f168baxte80.webp\"/><p> - · - </p></div>", "image": "https://raw.githubusercontent.com/xiaolin2004/gallery/master/GuangzhouZoo/DSC_1024-20241207_390.6f168baxte80.webp", "date_published": "2024-12-07 16:32:50", "date_modified": "2024-12-07 16:32:50"}, {"id": "https://raw.githubusercontent.com/xiaolin2004/gallery/master/GuangzhouZoo/DSC_1019-20241207_389.1557lmavthr4.webp", "url": "https://xiaolin2004.github.io/gallery?name=GuangzhouZoo/DSC_1019-20241207_389.1557lmavthr4.webp", "external_url": "https://xiaolin2004.github.io/gallery?name=GuangzhouZoo/DSC_1019-20241207_389.1557lmavthr4.webp", "title": "DSC_1019-20241207_389.1557lmavthr4", "content_html": "<div><img src=\"https://raw.githubusercontent.com/xiaolin2004/gallery/master/GuangzhouZoo/DSC_1019-20241207_389.1557lmavthr4.webp\"/><p> - · - </p></div>", "image": "https://raw.githubusercontent.com/xiaolin2004/gallery/master/GuangzhouZoo/DSC_1019-20241207_389.1557lmavthr4.webp", "date_published": "2024-12-07 16:30:18", "date_modified": "2024-12-07 16:30:18"}, {"id": "https://raw.githubusercontent.com/xiaolin2004/gallery/master/GuangzhouZoo/DSC_1016-20241207_388.2nsf8t8evto0.webp", "url": "https://xiaolin2004.github.io/gallery?name=GuangzhouZoo/DSC_1016-20241207_388.2nsf8t8evto0.webp", "external_url": "https://xiaolin2004.github.io/gallery?name=GuangzhouZoo/DSC_1016-20241207_388.2nsf8t8evto0.webp", "title": "DSC_1016-20241207_388.2nsf8t8evto0", "content_html": "<div><img src=\"https://raw.githubusercontent.com/xiaolin2004/gallery/master/GuangzhouZoo/DSC_1016-20241207_388.2nsf8t8evto0.webp\"/><p> - · - </p></div>", "image": "https://raw.githubusercontent.com/xiaolin2004/gallery/master/GuangzhouZoo/DSC_1016-20241207_388.2nsf8t8evto0.webp", "date_published": "2024-12-07 16:30:05", "date_modified": "2024-12-07 16:30:05"}, {"id": "https://raw.githubusercontent.com/xiaolin2004/gallery/master/GuangzhouZoo/DSC_1014-20241207_387.2sort5ncdy40.webp", "url": "https://xiaolin2004.github.io/gallery?name=GuangzhouZoo/DSC_1014-20241207_387.2sort5ncdy40.webp", "external_url": "https://xiaolin2004.github.io/gallery?name=GuangzhouZoo/DSC_1014-20241207_387.2sort5ncdy40.webp", "title": "DSC_1014-20241207_387.2sort5ncdy40", "content_html": "<div><img src=\"https://raw.githubusercontent.com/xiaolin2004/gallery/master/GuangzhouZoo/DSC_1014-20241207_387.2sort5ncdy40.webp\"/><p> - · - </p></div>", "image": "https://raw.githubusercontent.com/xiaolin2004/gallery/master/GuangzhouZoo/DSC_1014-20241207_387.2sort5ncdy40.webp", "date_published": "2024-12-07 16:29:42", "date_modified": "2024-12-07 16:29:42"}, {"id": "https://raw.githubusercontent.com/xiaolin2004/gallery/master/GuangzhouZoo/DSC_1013-20241207_386.5x1vcg86bew0.webp", "url": "https://xiaolin2004.github.io/gallery?name=GuangzhouZoo/DSC_1013-20241207_386.5x1vcg86bew0.webp", "external_url": "https://xiaolin2004.github.io/gallery?name=GuangzhouZoo/DSC_1013-20241207_386.5x1vcg86bew0.webp", "title": "DSC_1013-20241207_386.5x1vcg86bew0", "content_html": "<div><img src=\"https://raw.githubusercontent.com/xiaolin2004/gallery/master/GuangzhouZoo/DSC_1013-20241207_386.5x1vcg86bew0.webp\"/><p> - · - </p></div>", "image": "https://raw.githubusercontent.com/xiaolin2004/gallery/master/GuangzhouZoo/DSC_1013-20241207_386.5x1vcg86bew0.webp", "date_published": "2024-12-07 16:29:27", "date_modified": "2024-12-07 16:29:27"}, {"id": "https://raw.githubusercontent.com/xiaolin2004/gallery/master/GuangzhouZoo/DSC_1008-20241207_385.4uwaq0xpkxw0.webp", "url": "https://xiaolin2004.github.io/gallery?name=GuangzhouZoo/DSC_1008-20241207_385.4uwaq0xpkxw0.webp", "external_url": "https://xiaolin2004.github.io/gallery?name=GuangzhouZoo/DSC_1008-20241207_385.4uwaq0xpkxw0.webp", "title": "DSC_1008-20241207_385.4uwaq0xpkxw0", "content_html": "<div><img src=\"https://raw.githubusercontent.com/xiaolin2004/gallery/master/GuangzhouZoo/DSC_1008-20241207_385.4uwaq0xpkxw0.webp\"/><p> - · - </p></div>", "image": "https://raw.githubusercontent.com/xiaolin2004/gallery/master/GuangzhouZoo/DSC_1008-20241207_385.4uwaq0xpkxw0.webp", "date_published": "2024-12-07 16:28:56", "date_modified": "2024-12-07 16:28:56"}, {"id": "https://raw.githubusercontent.com/xiaolin2004/gallery/master/GuangzhouZoo/DSC_1003-20241207_384.2hnynh8bjwc0.webp", "url": "https://xiaolin2004.github.io/gallery?name=GuangzhouZoo/DSC_1003-20241207_384.2hnynh8bjwc0.webp", "external_url": "https://xiaolin2004.github.io/gallery?name=GuangzhouZoo/DSC_1003-20241207_384.2hnynh8bjwc0.webp", "title": "DSC_1003-20241207_384.2hnynh8bjwc0", "content_html": "<div><img src=\"https://raw.githubusercontent.com/xiaolin2004/gallery/master/GuangzhouZoo/DSC_1003-20241207_384.2hnynh8bjwc0.webp\"/><p> - · - </p></div>", "image": "https://raw.githubusercontent.com/xiaolin2004/gallery/master/GuangzhouZoo/DSC_1003-20241207_384.2hnynh8bjwc0.webp", "date_published": "2024-12-07 16:27:51", "date_modified": "2024-12-07 16:27:51"}, {"id": "https://raw.githubusercontent.com/xiaolin2004/gallery/master/GuangzhouZoo/DSC_1001-20241207_383.547gw91ytrc0.webp", "url": "https://xiaolin2004.github.io/gallery?name=GuangzhouZoo/DSC_1001-20241207_383.547gw91ytrc0.webp", "external_url": "https://xiaolin2004.github.io/gallery?name=GuangzhouZoo/DSC_1001-20241207_383.547gw91ytrc0.webp", "title": "DSC_1001-20241207_383.547gw91ytrc0", "content_html": "<div><img src=\"https://raw.githubusercontent.com/xiaolin2004/gallery/master/GuangzhouZoo/DSC_1001-20241207_383.547gw91ytrc0.webp\"/><p> - · - </p></div>", "image": "https://raw.githubusercontent.com/xiaolin2004/gallery/master/GuangzhouZoo/DSC_1001-20241207_383.547gw91ytrc0.webp", "date_published": "2024-12-07 16:27:45", "date_modified": "2024-12-07 16:27:45"}, {"id": "https://raw.githubusercontent.com/xiaolin2004/gallery/master/GuangzhouZoo/DSC_1000-20241207_382.5w8bxn940s00.webp", "url": "https://xiaolin2004.github.io/gallery?name=GuangzhouZoo/DSC_1000-20241207_382.5w8bxn940s00.webp", "external_url": "https://xiaolin2004.github.io/gallery?name=GuangzhouZoo/DSC_1000-20241207_382.5w8bxn940s00.webp", "title": "DSC_1000-20241207_382.5w8bxn940s00", "content_html": "<div><img src=\"https://raw.githubusercontent.com/xiaolin2004/gallery/master/GuangzhouZoo/DSC_1000-20241207_382.5w8bxn940s00.webp\"/><p> - · - </p></div>", "image": "https://raw.githubusercontent.com/xiaolin2004/gallery/master/GuangzhouZoo/DSC_1000-20241207_382.5w8bxn940s00.webp", "date_published": "2024-12-07 16:27:27", "date_modified": "2024-12-07 16:27:27"}, {"id": "https://raw.githubusercontent.com/xiaolin2004/gallery/master/GuangzhouZoo/DSC_0999-20241207_381.t2vws1q9p40.webp", "url": "https://xiaolin2004.github.io/gallery?name=GuangzhouZoo/DSC_0999-20241207_381.t2vws1q9p40.webp", "external_url": "https://xiaolin2004.github.io/gallery?name=GuangzhouZoo/DSC_0999-20241207_381.t2vws1q9p40.webp", "title": "DSC_0999-20241207_381.t2vws1q9p40", "content_html": "<div><img src=\"https://raw.githubusercontent.com/xiaolin2004/gallery/master/GuangzhouZoo/DSC_0999-20241207_381.t2vws1q9p40.webp\"/><p> - · - </p></div>", "image": "https://raw.githubusercontent.com/xiaolin2004/gallery/master/GuangzhouZoo/DSC_0999-20241207_381.t2vws1q9p40.webp", "date_published": "2024-12-07 16:27:15", "date_modified": "2024-12-07 16:27:15"}, {"id": "https://raw.githubusercontent.com/xiaolin2004/gallery/master/GuangzhouZoo/DSC_0998-20241207_380.767iet5un0s0.webp", "url": "https://xiaolin2004.github.io/gallery?name=GuangzhouZoo/DSC_0998-20241207_380.767iet5un0s0.webp", "external_url": "https://xiaolin2004.github.io/gallery?name=GuangzhouZoo/DSC_0998-20241207_380.767iet5un0s0.webp", "title": "DSC_0998-20241207_380.767iet5un0s0", "content_html": "<div><img src=\"https://raw.githubusercontent.com/xiaolin2004/gallery/master/GuangzhouZoo/DSC_0998-20241207_380.767iet5un0s0.webp\"/><p> - · - </p></div>", "image": "https://raw.githubusercontent.com/xiaolin2004/gallery/master/GuangzhouZoo/DSC_0998-20241207_380.767iet5un0s0.webp", "date_published": "2024-12-07 16:27:06", "date_modified": "2024-12-07 16:27:06"}, {"id": "https://raw.githubusercontent.com/xiaolin2004/gallery/master/GuangzhouZoo/DSC_0997-20241207_379.736wlp44ssw0.webp", "url": "https://xiaolin2004.github.io/gallery?name=GuangzhouZoo/DSC_0997-20241207_379.736wlp44ssw0.webp", "external_url": "https://xiaolin2004.github.io/gallery?name=GuangzhouZoo/DSC_0997-20241207_379.736wlp44ssw0.webp", "title": "DSC_0997-20241207_379.736wlp44ssw0", "content_html": "<div><img src=\"https://raw.githubusercontent.com/xiaolin2004/gallery/master/GuangzhouZoo/DSC_0997-20241207_379.736wlp44ssw0.webp\"/><p> - · - </p></div>", "image": "https://raw.githubusercontent.com/xiaolin2004/gallery/master/GuangzhouZoo/DSC_0997-20241207_379.736wlp44ssw0.webp", "date_published": "2024-12-07 16:27:04", "date_modified": "2024-12-07 16:27:04"}, {"id": "https://raw.githubusercontent.com/xiaolin2004/gallery/master/GuangzhouZoo/DSC_0996-20241207_378.2n6d8bftyx40.webp", "url": "https://xiaolin2004.github.io/gallery?name=GuangzhouZoo/DSC_0996-20241207_378.2n6d8bftyx40.webp", "external_url": "https://xiaolin2004.github.io/gallery?name=GuangzhouZoo/DSC_0996-20241207_378.2n6d8bftyx40.webp", "title": "DSC_0996-20241207_378.2n6d8bftyx40", "content_html": "<div><img src=\"https://raw.githubusercontent.com/xiaolin2004/gallery/master/GuangzhouZoo/DSC_0996-20241207_378.2n6d8bftyx40.webp\"/><p> - · - </p></div>", "image": "https://raw.githubusercontent.com/xiaolin2004/gallery/master/GuangzhouZoo/DSC_0996-20241207_378.2n6d8bftyx40.webp", "date_published": "2024-12-07 16:26:55", "date_modified": "2024-12-07 16:26:55"}, {"id": "https://raw.githubusercontent.com/xiaolin2004/gallery/master/GuangzhouZoo/DSC_0994-20241207_377.209c5ku3nrc0.webp", "url": "https://xiaolin2004.github.io/gallery?name=GuangzhouZoo/DSC_0994-20241207_377.209c5ku3nrc0.webp", "external_url": "https://xiaolin2004.github.io/gallery?name=GuangzhouZoo/DSC_0994-20241207_377.209c5ku3nrc0.webp", "title": "DSC_0994-20241207_377.209c5ku3nrc0", "content_html": "<div><img src=\"https://raw.githubusercontent.com/xiaolin2004/gallery/master/GuangzhouZoo/DSC_0994-20241207_377.209c5ku3nrc0.webp\"/><p> - · - </p></div>", "image": "https://raw.githubusercontent.com/xiaolin2004/gallery/master/GuangzhouZoo/DSC_0994-20241207_377.209c5ku3nrc0.webp", "date_published": "2024-12-07 16:26:50", "date_modified": "2024-12-07 16:26:50"}, {"id": "https://raw.githubusercontent.com/xiaolin2004/gallery/master/GuangzhouZoo/DSC_0993-20241207_376.46qgt16ssg80.webp", "url": "https://xiaolin2004.github.io/gallery?name=GuangzhouZoo/DSC_0993-20241207_376.46qgt16ssg80.webp", "external_url": "https://xiaolin2004.github.io/gallery?name=GuangzhouZoo/DSC_0993-20241207_376.46qgt16ssg80.webp", "title": "DSC_0993-20241207_376.46qgt16ssg80", "content_html": "<div><img src=\"https://raw.githubusercontent.com/xiaolin2004/gallery/master/GuangzhouZoo/DSC_0993-20241207_376.46qgt16ssg80.webp\"/><p> - · - </p></div>", "image": "https://raw.githubusercontent.com/xiaolin2004/gallery/master/GuangzhouZoo/DSC_0993-20241207_376.46qgt16ssg80.webp", "date_published": "2024-12-07 16:26:49", "date_modified": "2024-12-07 16:26:49"}, {"id": "https://raw.githubusercontent.com/xiaolin2004/gallery/master/GuangzhouZoo/DSC_0990-20241207_375.1x5dtqy0cz6o.webp", "url": "https://xiaolin2004.github.io/gallery?name=GuangzhouZoo/DSC_0990-20241207_375.1x5dtqy0cz6o.webp", "external_url": "https://xiaolin2004.github.io/gallery?name=GuangzhouZoo/DSC_0990-20241207_375.1x5dtqy0cz6o.webp", "title": "DSC_0990-20241207_375.1x5dtqy0cz6o", "content_html": "<div><img src=\"https://raw.githubusercontent.com/xiaolin2004/gallery/master/GuangzhouZoo/DSC_0990-20241207_375.1x5dtqy0cz6o.webp\"/><p> - · - </p></div>", "image": "https://raw.githubusercontent.com/xiaolin2004/gallery/master/GuangzhouZoo/DSC_0990-20241207_375.1x5dtqy0cz6o.webp", "date_published": "2024-12-07 16:26:34", "date_modified": "2024-12-07 16:26:34"}, {"id": "https://raw.githubusercontent.com/xiaolin2004/gallery/master/GuangzhouZoo/DSC_0989-20241207_374.5gkmi4bz7ug0.webp", "url": "https://xiaolin2004.github.io/gallery?name=GuangzhouZoo/DSC_0989-20241207_374.5gkmi4bz7ug0.webp", "external_url": "https://xiaolin2004.github.io/gallery?name=GuangzhouZoo/DSC_0989-20241207_374.5gkmi4bz7ug0.webp", "title": "DSC_0989-20241207_374.5gkmi4bz7ug0", "content_html": "<div><img src=\"https://raw.githubusercontent.com/xiaolin2004/gallery/master/GuangzhouZoo/DSC_0989-20241207_374.5gkmi4bz7ug0.webp\"/><p> - · - </p></div>", "image": "https://raw.githubusercontent.com/xiaolin2004/gallery/master/GuangzhouZoo/DSC_0989-20241207_374.5gkmi4bz7ug0.webp", "date_published": "2024-12-07 16:26:32", "date_modified": "2024-12-07 16:26:32"}, {"id": "https://raw.githubusercontent.com/xiaolin2004/gallery/master/GuangzhouZoo/DSC_0986-20241207_373.78e6mohmyas0.webp", "url": "https://xiaolin2004.github.io/gallery?name=GuangzhouZoo/DSC_0986-20241207_373.78e6mohmyas0.webp", "external_url": "https://xiaolin2004.github.io/gallery?name=GuangzhouZoo/DSC_0986-20241207_373.78e6mohmyas0.webp", "title": "DSC_0986-20241207_373.78e6mohmyas0", "content_html": "<div><img src=\"https://raw.githubusercontent.com/xiaolin2004/gallery/master/GuangzhouZoo/DSC_0986-20241207_373.78e6mohmyas0.webp\"/><p> - · - </p></div>", "image": "https://raw.githubusercontent.com/xiaolin2004/gallery/master/GuangzhouZoo/DSC_0986-20241207_373.78e6mohmyas0.webp", "date_published": "2024-12-07 16:26:04", "date_modified": "2024-12-07 16:26:04"}, {"id": "https://raw.githubusercontent.com/xiaolin2004/gallery/master/GuangzhouZoo/DSC_0984-20241207_372.72hzsj5rgpo0.webp", "url": "https://xiaolin2004.github.io/gallery?name=GuangzhouZoo/DSC_0984-20241207_372.72hzsj5rgpo0.webp", "external_url": "https://xiaolin2004.github.io/gallery?name=GuangzhouZoo/DSC_0984-20241207_372.72hzsj5rgpo0.webp", "title": "DSC_0984-20241207_372.72hzsj5rgpo0", "content_html": "<div><img src=\"https://raw.githubusercontent.com/xiaolin2004/gallery/master/GuangzhouZoo/DSC_0984-20241207_372.72hzsj5rgpo0.webp\"/><p> - · - </p></div>", "image": "https://raw.githubusercontent.com/xiaolin2004/gallery/master/GuangzhouZoo/DSC_0984-20241207_372.72hzsj5rgpo0.webp", "date_published": "2024-12-07 16:25:46", "date_modified": "2024-12-07 16:25:46"}, {"id": "https://raw.githubusercontent.com/xiaolin2004/gallery/master/GuangzhouZoo/DSC_0983-20241207_371.766q1xo46ew0.webp", "url": "https://xiaolin2004.github.io/gallery?name=GuangzhouZoo/DSC_0983-20241207_371.766q1xo46ew0.webp", "external_url": "https://xiaolin2004.github.io/gallery?name=GuangzhouZoo/DSC_0983-20241207_371.766q1xo46ew0.webp", "title": "DSC_0983-20241207_371.766q1xo46ew0", "content_html": "<div><img src=\"https://raw.githubusercontent.com/xiaolin2004/gallery/master/GuangzhouZoo/DSC_0983-20241207_371.766q1xo46ew0.webp\"/><p> - · - </p></div>", "image": "https://raw.githubusercontent.com/xiaolin2004/gallery/master/GuangzhouZoo/DSC_0983-20241207_371.766q1xo46ew0.webp", "date_published": "2024-12-07 16:25:36", "date_modified": "2024-12-07 16:25:36"}, {"id": "https://raw.githubusercontent.com/xiaolin2004/gallery/master/GuangzhouZoo/DSC_0978-20241207_370.2kzau0d6fc40.webp", "url": "https://xiaolin2004.github.io/gallery?name=GuangzhouZoo/DSC_0978-20241207_370.2kzau0d6fc40.webp", "external_url": "https://xiaolin2004.github.io/gallery?name=GuangzhouZoo/DSC_0978-20241207_370.2kzau0d6fc40.webp", "title": "DSC_0978-20241207_370.2kzau0d6fc40", "content_html": "<div><img src=\"https://raw.githubusercontent.com/xiaolin2004/gallery/master/GuangzhouZoo/DSC_0978-20241207_370.2kzau0d6fc40.webp\"/><p> - · - </p></div>", "image": "https://raw.githubusercontent.com/xiaolin2004/gallery/master/GuangzhouZoo/DSC_0978-20241207_370.2kzau0d6fc40.webp", "date_published": "2024-12-07 16:24:42", "date_modified": "2024-12-07 16:24:42"}, {"id": "https://raw.githubusercontent.com/xiaolin2004/gallery/master/GuangzhouZoo/DSC_0977-20241207_369.4vfaump2gi00.webp", "url": "https://xiaolin2004.github.io/gallery?name=GuangzhouZoo/DSC_0977-20241207_369.4vfaump2gi00.webp", "external_url": "https://xiaolin2004.github.io/gallery?name=GuangzhouZoo/DSC_0977-20241207_369.4vfaump2gi00.webp", "title": "DSC_0977-20241207_369.4vfaump2gi00", "content_html": "<div><img src=\"https://raw.githubusercontent.com/xiaolin2004/gallery/master/GuangzhouZoo/DSC_0977-20241207_369.4vfaump2gi00.webp\"/><p> - · - </p></div>", "image": "https://raw.githubusercontent.com/xiaolin2004/gallery/master/GuangzhouZoo/DSC_0977-20241207_369.4vfaump2gi00.webp", "date_published": "2024-12-07 16:24:37", "date_modified": "2024-12-07 16:24:37"}, {"id": "https://raw.githubusercontent.com/xiaolin2004/gallery/master/GuangzhouZoo/DSC_0975-20241207_368.6hqukse308c0.webp", "url": "https://xiaolin2004.github.io/gallery?name=GuangzhouZoo/DSC_0975-20241207_368.6hqukse308c0.webp", "external_url": "https://xiaolin2004.github.io/gallery?name=GuangzhouZoo/DSC_0975-20241207_368.6hqukse308c0.webp", "title": "DSC_0975-20241207_368.6hqukse308c0", "content_html": "<div><img src=\"https://raw.githubusercontent.com/xiaolin2004/gallery/master/GuangzhouZoo/DSC_0975-20241207_368.6hqukse308c0.webp\"/><p> - · - </p></div>", "image": "https://raw.githubusercontent.com/xiaolin2004/gallery/master/GuangzhouZoo/DSC_0975-20241207_368.6hqukse308c0.webp", "date_published": "2024-12-07 16:24:35", "date_modified": "2024-12-07 16:24:35"}, {"id": "https://raw.githubusercontent.com/xiaolin2004/gallery/master/GuangzhouZoo/DSC_0973-20241207_367.44pi6i6lbjk0.webp", "url": "https://xiaolin2004.github.io/gallery?name=GuangzhouZoo/DSC_0973-20241207_367.44pi6i6lbjk0.webp", "external_url": "https://xiaolin2004.github.io/gallery?name=GuangzhouZoo/DSC_0973-20241207_367.44pi6i6lbjk0.webp", "title": "DSC_0973-20241207_367.44pi6i6lbjk0", "content_html": "<div><img src=\"https://raw.githubusercontent.com/xiaolin2004/gallery/master/GuangzhouZoo/DSC_0973-20241207_367.44pi6i6lbjk0.webp\"/><p> - · - </p></div>", "image": "https://raw.githubusercontent.com/xiaolin2004/gallery/master/GuangzhouZoo/DSC_0973-20241207_367.44pi6i6lbjk0.webp", "date_published": "2024-12-07 16:24:08", "date_modified": "2024-12-07 16:24:08"}, {"id": "https://raw.githubusercontent.com/xiaolin2004/gallery/master/GuangzhouZoo/DSC_0968-20241207_366.5uphj8kt5r00.webp", "url": "https://xiaolin2004.github.io/gallery?name=GuangzhouZoo/DSC_0968-20241207_366.5uphj8kt5r00.webp", "external_url": "https://xiaolin2004.github.io/gallery?name=GuangzhouZoo/DSC_0968-20241207_366.5uphj8kt5r00.webp", "title": "DSC_0968-20241207_366.5uphj8kt5r00", "content_html": "<div><img src=\"https://raw.githubusercontent.com/xiaolin2004/gallery/master/GuangzhouZoo/DSC_0968-20241207_366.5uphj8kt5r00.webp\"/><p> - · - </p></div>", "image": "https://raw.githubusercontent.com/xiaolin2004/gallery/master/GuangzhouZoo/DSC_0968-20241207_366.5uphj8kt5r00.webp", "date_published": "2024-12-07 16:22:41", "date_modified": "2024-12-07 16:22:41"}, {"id": "https://raw.githubusercontent.com/xiaolin2004/gallery/master/GuangzhouZoo/DSC_0965-20241207_365.14bo6tbtiuo0.webp", "url": "https://xiaolin2004.github.io/gallery?name=GuangzhouZoo/DSC_0965-20241207_365.14bo6tbtiuo0.webp", "external_url": "https://xiaolin2004.github.io/gallery?name=GuangzhouZoo/DSC_0965-20241207_365.14bo6tbtiuo0.webp", "title": "DSC_0965-20241207_365.14bo6tbtiuo0", "content_html": "<div><img src=\"https://raw.githubusercontent.com/xiaolin2004/gallery/master/GuangzhouZoo/DSC_0965-20241207_365.14bo6tbtiuo0.webp\"/><p> - · - </p></div>", "image": "https://raw.githubusercontent.com/xiaolin2004/gallery/master/GuangzhouZoo/DSC_0965-20241207_365.14bo6tbtiuo0.webp", "date_published": "2024-12-07 16:22:14", "date_modified": "2024-12-07 16:22:14"}, {"id": "https://raw.githubusercontent.com/xiaolin2004/gallery/master/GuangzhouZoo/DSC_0963-20241207_363.5z4i8c5kilc0.webp", "url": "https://xiaolin2004.github.io/gallery?name=GuangzhouZoo/DSC_0963-20241207_363.5z4i8c5kilc0.webp", "external_url": "https://xiaolin2004.github.io/gallery?name=GuangzhouZoo/DSC_0963-20241207_363.5z4i8c5kilc0.webp", "title": "DSC_0963-20241207_363.5z4i8c5kilc0", "content_html": "<div><img src=\"https://raw.githubusercontent.com/xiaolin2004/gallery/master/GuangzhouZoo/DSC_0963-20241207_363.5z4i8c5kilc0.webp\"/><p> - · - </p></div>", "image": "https://raw.githubusercontent.com/xiaolin2004/gallery/master/GuangzhouZoo/DSC_0963-20241207_363.5z4i8c5kilc0.webp", "date_published": "2024-12-07 16:22:08", "date_modified": "2024-12-07 16:22:08"}, {"id": "https://raw.githubusercontent.com/xiaolin2004/gallery/master/GuangzhouZoo/DSC_0964-20241207_364.6utepvb1rs80.webp", "url": "https://xiaolin2004.github.io/gallery?name=GuangzhouZoo/DSC_0964-20241207_364.6utepvb1rs80.webp", "external_url": "https://xiaolin2004.github.io/gallery?name=GuangzhouZoo/DSC_0964-20241207_364.6utepvb1rs80.webp", "title": "DSC_0964-20241207_364.6utepvb1rs80", "content_html": "<div><img src=\"https://raw.githubusercontent.com/xiaolin2004/gallery/master/GuangzhouZoo/DSC_0964-20241207_364.6utepvb1rs80.webp\"/><p> - · - </p></div>", "image": "https://raw.githubusercontent.com/xiaolin2004/gallery/master/GuangzhouZoo/DSC_0964-20241207_364.6utepvb1rs80.webp", "date_published": "2024-12-07 16:22:08", "date_modified": "2024-12-07 16:22:08"}, {"id": "https://raw.githubusercontent.com/xiaolin2004/gallery/master/GuangzhouZoo/DSC_0962-20241207_362.6skv5f6n42g0.webp", "url": "https://xiaolin2004.github.io/gallery?name=GuangzhouZoo/DSC_0962-20241207_362.6skv5f6n42g0.webp", "external_url": "https://xiaolin2004.github.io/gallery?name=GuangzhouZoo/DSC_0962-20241207_362.6skv5f6n42g0.webp", "title": "DSC_0962-20241207_362.6skv5f6n42g0", "content_html": "<div><img src=\"https://raw.githubusercontent.com/xiaolin2004/gallery/master/GuangzhouZoo/DSC_0962-20241207_362.6skv5f6n42g0.webp\"/><p> - · - </p></div>", "image": "https://raw.githubusercontent.com/xiaolin2004/gallery/master/GuangzhouZoo/DSC_0962-20241207_362.6skv5f6n42g0.webp", "date_published": "2024-12-07 16:21:12", "date_modified": "2024-12-07 16:21:12"}, {"id": "https://raw.githubusercontent.com/xiaolin2004/gallery/master/GuangzhouZoo/DSC_0961-20241207_361.3xei9xkt30y0.webp", "url": "https://xiaolin2004.github.io/gallery?name=GuangzhouZoo/DSC_0961-20241207_361.3xei9xkt30y0.webp", "external_url": "https://xiaolin2004.github.io/gallery?name=GuangzhouZoo/DSC_0961-20241207_361.3xei9xkt30y0.webp", "title": "DSC_0961-20241207_361.3xei9xkt30y0", "content_html": "<div><img src=\"https://raw.githubusercontent.com/xiaolin2004/gallery/master/GuangzhouZoo/DSC_0961-20241207_361.3xei9xkt30y0.webp\"/><p> - · - </p></div>", "image": "https://raw.githubusercontent.com/xiaolin2004/gallery/master/GuangzhouZoo/DSC_0961-20241207_361.3xei9xkt30y0.webp", "date_published": "2024-12-07 16:20:45", "date_modified": "2024-12-07 16:20:45"}, {"id": "https://raw.githubusercontent.com/xiaolin2004/gallery/master/GuangzhouZoo/DSC_0959-20241207_360.5jxcb6kvec80.webp", "url": "https://xiaolin2004.github.io/gallery?name=GuangzhouZoo/DSC_0959-20241207_360.5jxcb6kvec80.webp", "external_url": "https://xiaolin2004.github.io/gallery?name=GuangzhouZoo/DSC_0959-20241207_360.5jxcb6kvec80.webp", "title": "DSC_0959-20241207_360.5jxcb6kvec80", "content_html": "<div><img src=\"https://raw.githubusercontent.com/xiaolin2004/gallery/master/GuangzhouZoo/DSC_0959-20241207_360.5jxcb6kvec80.webp\"/><p> - · - </p></div>", "image": "https://raw.githubusercontent.com/xiaolin2004/gallery/master/GuangzhouZoo/DSC_0959-20241207_360.5jxcb6kvec80.webp", "date_published": "2024-12-07 16:20:26", "date_modified": "2024-12-07 16:20:26"}, {"id": "https://raw.githubusercontent.com/xiaolin2004/gallery/master/GuangzhouZoo/DSC_0958-20241207_359.4lteazho6ge0.webp", "url": "https://xiaolin2004.github.io/gallery?name=GuangzhouZoo/DSC_0958-20241207_359.4lteazho6ge0.webp", "external_url": "https://xiaolin2004.github.io/gallery?name=GuangzhouZoo/DSC_0958-20241207_359.4lteazho6ge0.webp", "title": "DSC_0958-20241207_359.4lteazho6ge0", "content_html": "<div><img src=\"https://raw.githubusercontent.com/xiaolin2004/gallery/master/GuangzhouZoo/DSC_0958-20241207_359.4lteazho6ge0.webp\"/><p> - · - </p></div>", "image": "https://raw.githubusercontent.com/xiaolin2004/gallery/master/GuangzhouZoo/DSC_0958-20241207_359.4lteazho6ge0.webp", "date_published": "2024-12-07 16:20:22", "date_modified": "2024-12-07 16:20:22"}, {"id": "https://raw.githubusercontent.com/xiaolin2004/gallery/master/GuangzhouZoo/DSC_0954-20241207_358.6td0xp1o3n80.webp", "url": "https://xiaolin2004.github.io/gallery?name=GuangzhouZoo/DSC_0954-20241207_358.6td0xp1o3n80.webp", "external_url": "https://xiaolin2004.github.io/gallery?name=GuangzhouZoo/DSC_0954-20241207_358.6td0xp1o3n80.webp", "title": "DSC_0954-20241207_358.6td0xp1o3n80", "content_html": "<div><img src=\"https://raw.githubusercontent.com/xiaolin2004/gallery/master/GuangzhouZoo/DSC_0954-20241207_358.6td0xp1o3n80.webp\"/><p> - · - </p></div>", "image": "https://raw.githubusercontent.com/xiaolin2004/gallery/master/GuangzhouZoo/DSC_0954-20241207_358.6td0xp1o3n80.webp", "date_published": "2024-12-07 16:19:47", "date_modified": "2024-12-07 16:19:47"}, {"id": "https://raw.githubusercontent.com/xiaolin2004/gallery/master/GuangzhouZoo/DSC_0943-20241207_357.71szfr9objo0.webp", "url": "https://xiaolin2004.github.io/gallery?name=GuangzhouZoo/DSC_0943-20241207_357.71szfr9objo0.webp", "external_url": "https://xiaolin2004.github.io/gallery?name=GuangzhouZoo/DSC_0943-20241207_357.71szfr9objo0.webp", "title": "DSC_0943-20241207_357.71szfr9objo0", "content_html": "<div><img src=\"https://raw.githubusercontent.com/xiaolin2004/gallery/master/GuangzhouZoo/DSC_0943-20241207_357.71szfr9objo0.webp\"/><p> - · - </p></div>", "image": "https://raw.githubusercontent.com/xiaolin2004/gallery/master/GuangzhouZoo/DSC_0943-20241207_357.71szfr9objo0.webp", "date_published": "2024-12-07 16:17:58", "date_modified": "2024-12-07 16:17:58"}, {"id": "https://raw.githubusercontent.com/xiaolin2004/gallery/master/GuangzhouZoo/DSC_0942-20241207_356.6e14vaik7rs0.webp", "url": "https://xiaolin2004.github.io/gallery?name=GuangzhouZoo/DSC_0942-20241207_356.6e14vaik7rs0.webp", "external_url": "https://xiaolin2004.github.io/gallery?name=GuangzhouZoo/DSC_0942-20241207_356.6e14vaik7rs0.webp", "title": "DSC_0942-20241207_356.6e14vaik7rs0", "content_html": "<div><img src=\"https://raw.githubusercontent.com/xiaolin2004/gallery/master/GuangzhouZoo/DSC_0942-20241207_356.6e14vaik7rs0.webp\"/><p> - · - </p></div>", "image": "https://raw.githubusercontent.com/xiaolin2004/gallery/master/GuangzhouZoo/DSC_0942-20241207_356.6e14vaik7rs0.webp", "date_published": "2024-12-07 16:14:57", "date_modified": "2024-12-07 16:14:57"}, {"id": "https://raw.githubusercontent.com/xiaolin2004/gallery/master/GuangzhouZoo/DSC_0941-20241207_355.5qv1ohqvlo40.webp", "url": "https://xiaolin2004.github.io/gallery?name=GuangzhouZoo/DSC_0941-20241207_355.5qv1ohqvlo40.webp", "external_url": "https://xiaolin2004.github.io/gallery?name=GuangzhouZoo/DSC_0941-20241207_355.5qv1ohqvlo40.webp", "title": "DSC_0941-20241207_355.5qv1ohqvlo40", "content_html": "<div><img src=\"https://raw.githubusercontent.com/xiaolin2004/gallery/master/GuangzhouZoo/DSC_0941-20241207_355.5qv1ohqvlo40.webp\"/><p> - · - </p></div>", "image": "https://raw.githubusercontent.com/xiaolin2004/gallery/master/GuangzhouZoo/DSC_0941-20241207_355.5qv1ohqvlo40.webp", "date_published": "2024-12-07 16:12:25", "date_modified": "2024-12-07 16:12:25"}, {"id": "https://raw.githubusercontent.com/xiaolin2004/gallery/master/GuangzhouZoo/DSC_0940-20241207_354.5kczx2hutc40.webp", "url": "https://xiaolin2004.github.io/gallery?name=GuangzhouZoo/DSC_0940-20241207_354.5kczx2hutc40.webp", "external_url": "https://xiaolin2004.github.io/gallery?name=GuangzhouZoo/DSC_0940-20241207_354.5kczx2hutc40.webp", "title": "DSC_0940-20241207_354.5kczx2hutc40", "content_html": "<div><img src=\"https://raw.githubusercontent.com/xiaolin2004/gallery/master/GuangzhouZoo/DSC_0940-20241207_354.5kczx2hutc40.webp\"/><p> - · - </p></div>", "image": "https://raw.githubusercontent.com/xiaolin2004/gallery/master/GuangzhouZoo/DSC_0940-20241207_354.5kczx2hutc40.webp", "date_published": "2024-12-07 16:10:22", "date_modified": "2024-12-07 16:10:22"}, {"id": "https://raw.githubusercontent.com/xiaolin2004/gallery/master/GuangzhouZoo/DSC_0939-20241207_353.2y7dh7qaf420.webp", "url": "https://xiaolin2004.github.io/gallery?name=GuangzhouZoo/DSC_0939-20241207_353.2y7dh7qaf420.webp", "external_url": "https://xiaolin2004.github.io/gallery?name=GuangzhouZoo/DSC_0939-20241207_353.2y7dh7qaf420.webp", "title": "DSC_0939-20241207_353.2y7dh7qaf420", "content_html": "<div><img src=\"https://raw.githubusercontent.com/xiaolin2004/gallery/master/GuangzhouZoo/DSC_0939-20241207_353.2y7dh7qaf420.webp\"/><p> - · - </p></div>", "image": "https://raw.githubusercontent.com/xiaolin2004/gallery/master/GuangzhouZoo/DSC_0939-20241207_353.2y7dh7qaf420.webp", "date_published": "2024-12-07 16:10:08", "date_modified": "2024-12-07 16:10:08"}, {"id": "https://raw.githubusercontent.com/xiaolin2004/gallery/master/GuangzhouZoo/DSC_0938-20241207_352.1zxmc2dsjry8.webp", "url": "https://xiaolin2004.github.io/gallery?name=GuangzhouZoo/DSC_0938-20241207_352.1zxmc2dsjry8.webp", "external_url": "https://xiaolin2004.github.io/gallery?name=GuangzhouZoo/DSC_0938-20241207_352.1zxmc2dsjry8.webp", "title": "DSC_0938-20241207_352.1zxmc2dsjry8", "content_html": "<div><img src=\"https://raw.githubusercontent.com/xiaolin2004/gallery/master/GuangzhouZoo/DSC_0938-20241207_352.1zxmc2dsjry8.webp\"/><p> - · - </p></div>", "image": "https://raw.githubusercontent.com/xiaolin2004/gallery/master/GuangzhouZoo/DSC_0938-20241207_352.1zxmc2dsjry8.webp", "date_published": "2024-12-07 16:10:01", "date_modified": "2024-12-07 16:10:01"}, {"id": "https://raw.githubusercontent.com/xiaolin2004/gallery/master/GuangzhouZoo/DSC_0937-20241207_351.66etbn7c3ks0.webp", "url": "https://xiaolin2004.github.io/gallery?name=GuangzhouZoo/DSC_0937-20241207_351.66etbn7c3ks0.webp", "external_url": "https://xiaolin2004.github.io/gallery?name=GuangzhouZoo/DSC_0937-20241207_351.66etbn7c3ks0.webp", "title": "DSC_0937-20241207_351.66etbn7c3ks0", "content_html": "<div><img src=\"https://raw.githubusercontent.com/xiaolin2004/gallery/master/GuangzhouZoo/DSC_0937-20241207_351.66etbn7c3ks0.webp\"/><p> - · - </p></div>", "image": "https://raw.githubusercontent.com/xiaolin2004/gallery/master/GuangzhouZoo/DSC_0937-20241207_351.66etbn7c3ks0.webp", "date_published": "2024-12-07 16:10:00", "date_modified": "2024-12-07 16:10:00"}, {"id": "https://raw.githubusercontent.com/xiaolin2004/gallery/master/GuangzhouZoo/DSC_0934-20241207_350.42k41k14i8o0.webp", "url": "https://xiaolin2004.github.io/gallery?name=GuangzhouZoo/DSC_0934-20241207_350.42k41k14i8o0.webp", "external_url": "https://xiaolin2004.github.io/gallery?name=GuangzhouZoo/DSC_0934-20241207_350.42k41k14i8o0.webp", "title": "DSC_0934-20241207_350.42k41k14i8o0", "content_html": "<div><img src=\"https://raw.githubusercontent.com/xiaolin2004/gallery/master/GuangzhouZoo/DSC_0934-20241207_350.42k41k14i8o0.webp\"/><p> - · - </p></div>", "image": "https://raw.githubusercontent.com/xiaolin2004/gallery/master/GuangzhouZoo/DSC_0934-20241207_350.42k41k14i8o0.webp", "date_published": "2024-12-07 16:08:54", "date_modified": "2024-12-07 16:08:54"}, {"id": "https://raw.githubusercontent.com/xiaolin2004/gallery/master/GuangzhouZoo/DSC_0933-20241207_349.4tzesi49tqg0.webp", "url": "https://xiaolin2004.github.io/gallery?name=GuangzhouZoo/DSC_0933-20241207_349.4tzesi49tqg0.webp", "external_url": "https://xiaolin2004.github.io/gallery?name=GuangzhouZoo/DSC_0933-20241207_349.4tzesi49tqg0.webp", "title": "DSC_0933-20241207_349.4tzesi49tqg0", "content_html": "<div><img src=\"https://raw.githubusercontent.com/xiaolin2004/gallery/master/GuangzhouZoo/DSC_0933-20241207_349.4tzesi49tqg0.webp\"/><p> - · - </p></div>", "image": "https://raw.githubusercontent.com/xiaolin2004/gallery/master/GuangzhouZoo/DSC_0933-20241207_349.4tzesi49tqg0.webp", "date_published": "2024-12-07 16:08:50", "date_modified": "2024-12-07 16:08:50"}, {"id": "https://raw.githubusercontent.com/xiaolin2004/gallery/master/GuangzhouZoo/DSC_0931-20241205_347.4did1e3icbq0.webp", "url": "https://xiaolin2004.github.io/gallery?name=GuangzhouZoo/DSC_0931-20241205_347.4did1e3icbq0.webp", "external_url": "https://xiaolin2004.github.io/gallery?name=GuangzhouZoo/DSC_0931-20241205_347.4did1e3icbq0.webp", "title": "DSC_0931-20241205_347.4did1e3icbq0", "content_html": "<div><img src=\"https://raw.githubusercontent.com/xiaolin2004/gallery/master/GuangzhouZoo/DSC_0931-20241205_347.4did1e3icbq0.webp\"/><p> - · - </p></div>", "image": "https://raw.githubusercontent.com/xiaolin2004/gallery/master/GuangzhouZoo/DSC_0931-20241205_347.4did1e3icbq0.webp", "date_published": "2024-12-05 17:26:16", "date_modified": "2024-12-05 17:26:16"}, {"id": "https://raw.githubusercontent.com/xiaolin2004/gallery/master/Haizhu_wetland/6A230371-5C5B-4B53-9B7C-9A95A14CA3ED_1_102_o.3bgxak4y3l40.webp", "url": "https://xiaolin2004.github.io/gallery?name=Haizhu_wetland/6A230371-5C5B-4B53-9B7C-9A95A14CA3ED_1_102_o.3bgxak4y3l40.webp", "external_url": "https://xiaolin2004.github.io/gallery?name=Haizhu_wetland/6A230371-5C5B-4B53-9B7C-9A95A14CA3ED_1_102_o.3bgxak4y3l40.webp", "title": "6A230371-5C5B-4B53-9B7C-9A95A14CA3ED_1_102_o.3bgxak4y3l40", "content_html": "<div><img src=\"https://raw.githubusercontent.com/xiaolin2004/gallery/master/Haizhu_wetland/6A230371-5C5B-4B53-9B7C-9A95A14CA3ED_1_102_o.3bgxak4y3l40.webp\"/><p> - · - </p></div>", "image": "https://raw.githubusercontent.com/xiaolin2004/gallery/master/Haizhu_wetland/6A230371-5C5B-4B53-9B7C-9A95A14CA3ED_1_102_o.3bgxak4y3l40.webp", "date_published": "2024-10-19 13:30:53", "date_modified": "2024-10-19 13:30:53"}, {"id": "https://raw.githubusercontent.com/xiaolin2004/gallery/master/test/85338743-B055-43F2-BCC1-1397081B1450_1_102_o.1jur0p7840o0.webp", "url": "https://xiaolin2004.github.io/gallery?name=test/85338743-B055-43F2-BCC1-1397081B1450_1_102_o.1jur0p7840o0.webp", "external_url": "https://xiaolin2004.github.io/gallery?name=test/85338743-B055-43F2-BCC1-1397081B1450_1_102_o.1jur0p7840o0.webp", "title": "85338743-B055-43F2-BCC1-1397081B1450_1_102_o.1jur0p7840o0", "content_html": "<div><img src=\"https://raw.githubusercontent.com/xiaolin2004/gallery/master/test/85338743-B055-43F2-BCC1-1397081B1450_1_102_o.1jur0p7840o0.webp\"/><p>The image features a beautiful pond with a variety of lily pads and water lilies floating on the surface. There are at least thirteen lily pads and nine water lilies in the scene, creating a picturesque and serene atmosphere. The lily pads are spread across the pond, with some located closer to the foreground and others further away, giving the impression of a calm and peaceful environment.</p></div>", "image": "https://raw.githubusercontent.com/xiaolin2004/gallery/master/test/85338743-B055-43F2-BCC1-1397081B1450_1_102_o.1jur0p7840o0.webp", "date_published": "2024-10-19 11:42:47", "date_modified": "2024-10-19 11:42:47"}, {"id": "https://raw.githubusercontent.com/xiaolin2004/gallery/master/Haizhu_wetland/F4EECDC6-29AF-4A61-8B11-4AD161941D1F_1_102_o.cjh31irbrwg.webp", "url": "https://xiaolin2004.github.io/gallery?name=Haizhu_wetland/F4EECDC6-29AF-4A61-8B11-4AD161941D1F_1_102_o.cjh31irbrwg.webp", "external_url": "https://xiaolin2004.github.io/gallery?name=Haizhu_wetland/F4EECDC6-29AF-4A61-8B11-4AD161941D1F_1_102_o.cjh31irbrwg.webp", "title": "F4EECDC6-29AF-4A61-8B11-4AD161941D1F_1_102_o.cjh31irbrwg", "content_html": "<div><img src=\"https://raw.githubusercontent.com/xiaolin2004/gallery/master/Haizhu_wetland/F4EECDC6-29AF-4A61-8B11-4AD161941D1F_1_102_o.cjh31irbrwg.webp\"/><p> - · - </p></div>", "image": "https://raw.githubusercontent.com/xiaolin2004/gallery/master/Haizhu_wetland/F4EECDC6-29AF-4A61-8B11-4AD161941D1F_1_102_o.cjh31irbrwg.webp", "date_published": "2024-10-19 11:42:02", "date_modified": "2024-10-19 11:42:02"}, {"id": "https://raw.githubusercontent.com/xiaolin2004/gallery/master/Shanghai/IMG_2833.3s529jlc2a20.webp", "url": "https://xiaolin2004.github.io/gallery?name=Shanghai/IMG_2833.3s529jlc2a20.webp", "external_url": "https://xiaolin2004.github.io/gallery?name=Shanghai/IMG_2833.3s529jlc2a20.webp", "title": "IMG_2833.3s529jlc2a20", "content_html": "<div><img src=\"https://raw.githubusercontent.com/xiaolin2004/gallery/master/Shanghai/IMG_2833.3s529jlc2a20.webp\"/><p> - · - </p></div>", "image": "https://raw.githubusercontent.com/xiaolin2004/gallery/master/Shanghai/IMG_2833.3s529jlc2a20.webp", "date_published": "2024-01-19 20:34:26", "date_modified": "2024-01-19 20:34:26"}]}